ALU.sv
module ALU #(
    parameter DATAWIDTH = 32
)(
    input logic [DATAWIDTH-1:0]         ALUop1,
    input logic [2:0]                   ALUctrl,
    input logic                         ALUsrc,
    input logic [DATAWIDTH-1:0]         regOp2,
    input logic [DATAWIDTH-1:0]         ImmOp,
    // input logic clk,

    output logic [DATAWIDTH-1:0]        ALUout,
    output logic Eq
);

    logic [DATAWIDTH-1:0] ALUop2;
     
always_comb begin
    ALUop2 = ALUsrc ? ImmOp : regOp2;
    case (ALUctrl)
        3'b000: ALUout = ALUop1 + ALUop2;
        3'b001: ALUout= ALUop1 - ALUop2;
        3'b010: ALUout= ALUop1 & ALUop2;
        3'b011: ALUout= ALUop1 | ALUop2;
        3'b100: ALUout= 32'b0;
        3'b101: ALUout= 32'b0;
        3'b110: ALUout= 32'b0;
        default: ALUout = 0;
    endcase
    
end
assign Eq = (ALUop1==ALUop2);
// always_ff @(posedge clk) begin
//     $display("aluop1: ",ALUop1);
//     $display("aluop2: ",ALUop2);
//     $display("eq : ",Eq);
// end


endmodule

sign_extend.sv
module sign_extend #(
    parameter IMMSRC_WIDTH = 3,
            DATA_WIDTH = 32,
            imm_length = 12
)(
    input logic [DATA_WIDTH-1:0]        instr, // input instruction to extract immediate from 
    input logic [IMMSRC_WIDTH-1:0]      immsrc, // determines what type of immediate
    output logic [DATA_WIDTH-1:0]       immop // ImmOp, 32bits wide regardless
);


always_comb begin
    //asynchronous
    case (immsrc)
        000:    immop = {{(DATA_WIDTH - imm_length){instr[DATA_WIDTH-1]}}, instr[DATA_WIDTH-1:(DATA_WIDTH - imm_length)]};
                // regular immediate
                // 20*MSB concatenated with the 12-bit immediate
        001:    immop = {{(DATA_WIDTH - imm_length){instr[DATA_WIDTH-1]}}, instr[DATA_WIDTH-1:imm_length]};
                // upper immediate
                // 12*MSB concatenated with the 20-bit immediate

                //TODO: Is the +1 for 32bit constants being considered here or in the ALU??

        010:    immop = {{12{instr[DATA_WIDTH-1]}}, instr[31:25], instr[11:7]};
                // store | load

        011:    immop = {{12{instr[DATA_WIDTH-1]}}, instr[31], instr[11], instr[30:25], instr[11:8]};
                // branch
    
        // 100: jump case, ignoring for nowWIDTH'b0
        default: immop = {DATA_WIDTH{1'b0}};
    endcase
end
    
endmodule

register_file.sv
module register_file #(
    parameter ADDRESS_WIDTH = 5,
                DATA_WIDTH = 32
)(
    input logic                             clk,
    input logic [ADDRESS_WIDTH-1:0]         AD1,
    input logic [ADDRESS_WIDTH-1:0]         AD2,
    input logic [ADDRESS_WIDTH-1:0]         AD3,
    input logic                             WE3,
    input logic [DATA_WIDTH-1:0]            WD3,

    output logic [DATA_WIDTH-1:0]           RD1,
    output logic [DATA_WIDTH-1:0]           RD2,
    output logic [DATA_WIDTH-1:0]           a0  
);
//connecting mux logic: ALUsrc ? ImmOp : regOp2;

logic [DATA_WIDTH-1:0] register_array [2**ADDRESS_WIDTH-1:0];

always_ff @(posedge clk) begin
    if (WE3) register_array[AD3] <= WD3;
   
end
always_comb begin
    RD1 = register_array[AD1];
    RD2 = register_array[AD2];
end

always_comb begin
    $display("###########################################################");
    $display("registers");
    $display("t1");
    $displayh(register_array[6]);
    $display("a0");
    $displayh(register_array[10]);
    $display("a1");
    $displayh(register_array[11]);
end

assign  a0 = register_array[10];

endmodule

control.sv
module control #(
    parameter AW=32
) (
    input logic Eq,
    input logic [AW-1:0] instr,
    output logic RegWrite,
    output logic [2:0] ALUctrl,
    output logic ALUsrc,
    output logic [2:0] ImmSrc,
    output logic PCsrc 
);
    logic [6:0] opcode;
    
    always_comb begin
        opcode=instr[6:0];
        ALUctrl=instr[14:12];
        // ALUsrc=instr[5]? 0: 1;
        case (opcode)
            7'd19: begin //store inst
                 ImmSrc=3'b000;
                 RegWrite=1'b1;
                 PCsrc=1'b0;
                 ALUsrc=1'b1;
                end
            7'd99:begin //jump instr
                ImmSrc=3'b001;
                RegWrite=1'b0;
                PCsrc=Eq?1'b0:1'b1;
                ALUsrc=1'b0;
            end
         default: begin
            ImmSrc=3'b000;
            RegWrite=1'b0;
            PCsrc=1'b0;
        end          
        endcase

    end
endmodule

ROM.sv
module ROM #(
    parameter   ADDRESS_WIDTH = 8,
                DATA_WIDTH = 8,
                INS_WIDTH = 32
)(
    input logic     [ADDRESS_WIDTH-1:0]         A,
    output logic    [INS_WIDTH-1:0]             RD
);

logic [DATA_WIDTH-1:0] rom_array [2**ADDRESS_WIDTH-1:0];

initial begin
    $display("Loading rom.");
    $readmemh("example_rom.mem", rom_array);
end

always_comb begin
    //output is asynchronous
    RD = {rom_array[A], rom_array[A+1], rom_array[A+2], rom_array[A+3]}; //move along each word

    $displayh({rom_array[A], rom_array[A+1], rom_array[A+2], rom_array[A+3]});
    $display(A);
end

endmodule

PC.sv
module PC #(
    DW=32

) (
    input logic     clk,
    input logic     rst,
    input logic     PCsrc,
    input logic   [DW-1:0]  ImmOp,
    output logic  [DW-1:0]  PCC
);
    
    logic [DW-1:0] inc_PC;
    logic [DW-1:0] branch_PC;
    logic [DW-1:0] next_PC;

    assign branch_PC = PCC+ImmOp;
    assign inc_PC=PCC+4;
    assign next_PC=PCsrc ? branch_PC : inc_PC;
   
    always_comb begin
        
    end

    always_ff @(posedge clk ) begin
        // $display("PC= ",PCC);
        if (rst) PCC<=32'b0;
        else PCC<=next_PC;
    end

endmodule

top.sv
module top #(
    parameter DW=32
) (
    input logic clk,
    input logic rst,
    output logic [DW-1:0] a0out,
    output logic [DW-1:0] InstructionWire,
    output logic [DW-1:0] ImmOpWire 
);

    logic PCsrsWire;
    
    logic [DW-1:0] PCWire;
    
    logic [DW-1:0] ALUoutWire;
    logic [DW-1:0] RD1Wire;
    logic [DW-1:0] RD2Wire;
    logic EQWire;
    logic RegWriteWire;
    logic ALUsrcWire;
    logic [2:0] ALUctrlWire;
    logic [2:0] ImmSrcWire;
    logic [4:0] rs1;
    logic [4:0] rs2;
    logic [4:0] rd;
    
    PC PC(
        .clk(clk),
        .rst(rst),
        .PCsrc(PCsrsWire),
        .ImmOp(ImmOpWire),
        .PCC(PCWire)
    );
    
    ROM ROM(
        .A(PCWire),
        .RD(InstructionWire)
    );
   
    assign rs1 = InstructionWire[19:15];
    assign rs2 = InstructionWire[24:20];
    assign rd = InstructionWire[11:7];
    
    control control(
        .Eq(EQWire),
        .instr(InstructionWire),
        .RegWrite(RegWriteWire),
        .ALUctrl(ALUctrlWire),
        .ALUsrc(ALUsrcWire),
        .ImmSrc(ImmSrcWire),
        .PCsrc(PCsrsWire)
    );

    register_file RegFile(
        .clk(clk),
        .AD1(rs1),
        .AD2(rs2),
        .AD3(rd),
        .WE3(RegWriteWire),
        .WD3(ALUoutWire),

        .a0(a0out),
        .RD1(RD1Wire),
        .RD2(RD2Wire)
    );
    sign_extend extend(
        .instr(InstructionWire),
        .immsrc(ImmSrcWire),
        .immop(ImmOpWire)
    );
    ALU aluCPU(
        .ALUop1(RD1Wire),
        .ALUctrl(ALUctrlWire),
        .ALUsrc(ALUsrcWire),
        .regOp2(RD2Wire), //register
        .ImmOp(ImmOpWire), //immediate comparison done inside alu

        .ALUout(ALUoutWire),
        .Eq(EQWire)
    );
    

    
endmodule

top.vcd
$version Generated by VerilatedVcd $end
$date Wed Nov 23 15:11:19 2022 $end
$timescale 1ps $end

 $scope module TOP $end
  $var wire 32 S ImmOpWire [31:0] $end
  $var wire 32 R InstructionWire [31:0] $end
  $var wire 32 Q a0out [31:0] $end
  $var wire  1 O clk $end
  $var wire  1 P rst $end
  $scope module top $end
   $var wire  3 V ALUctrlWire [2:0] $end
   $var wire 32 I ALUoutWire [31:0] $end
   $var wire  1 K ALUsrcWire $end
   $var wire 32 \ DW [31:0] $end
   $var wire  1 U EQWire $end
   $var wire 32 S ImmOpWire [31:0] $end
   $var wire  3 L ImmSrcWire [2:0] $end
   $var wire 32 R InstructionWire [31:0] $end
   $var wire 32 # PCWire [31:0] $end
   $var wire  1 H PCsrsWire $end
   $var wire 32 $ RD1Wire [31:0] $end
   $var wire 32 T RD2Wire [31:0] $end
   $var wire  1 J RegWriteWire $end
   $var wire 32 Q a0out [31:0] $end
   $var wire  1 O clk $end
   $var wire  5 Y rd [4:0] $end
   $var wire  5 W rs1 [4:0] $end
   $var wire  5 X rs2 [4:0] $end
   $var wire  1 P rst $end
   $scope module PC $end
    $var wire 32 \ DW [31:0] $end
    $var wire 32 S ImmOp [31:0] $end
    $var wire 32 # PCC [31:0] $end
    $var wire  1 H PCsrc $end
    $var wire 32 Z branch_PC [31:0] $end
    $var wire  1 O clk $end
    $var wire 32 % inc_PC [31:0] $end
    $var wire 32 [ next_PC [31:0] $end
    $var wire  1 P rst $end
   $upscope $end
   $scope module ROM $end
    $var wire  8 & A [7:0] $end
    $var wire 32 ] ADDRESS_WIDTH [31:0] $end
    $var wire 32 ] DATA_WIDTH [31:0] $end
    $var wire  8 ' RD [7:0] $end
   $upscope $end
   $scope module RegFile $end
    $var wire  5 W AD1 [4:0] $end
    $var wire  5 X AD2 [4:0] $end
    $var wire  5 Y AD3 [4:0] $end
    $var wire 32 ^ ADDRESS_WIDTH [31:0] $end
    $var wire 32 \ DATA_WIDTH [31:0] $end
    $var wire 32 $ RD1 [31:0] $end
    $var wire 32 T RD2 [31:0] $end
    $var wire 32 I WD3 [31:0] $end
    $var wire  1 J WE3 $end
    $var wire 32 Q a0 [31:0] $end
    $var wire  1 O clk $end
    $var wire 32 ( register_array[0] [31:0] $end
    $var wire 32 2 register_array[10] [31:0] $end
    $var wire 32 3 register_array[11] [31:0] $end
    $var wire 32 4 register_array[12] [31:0] $end
    $var wire 32 5 register_array[13] [31:0] $end
    $var wire 32 6 register_array[14] [31:0] $end
    $var wire 32 7 register_array[15] [31:0] $end
    $var wire 32 8 register_array[16] [31:0] $end
    $var wire 32 9 register_array[17] [31:0] $end
    $var wire 32 : register_array[18] [31:0] $end
    $var wire 32 ; register_array[19] [31:0] $end
    $var wire 32 ) register_array[1] [31:0] $end
    $var wire 32 < register_array[20] [31:0] $end
    $var wire 32 = register_array[21] [31:0] $end
    $var wire 32 > register_array[22] [31:0] $end
    $var wire 32 ? register_array[23] [31:0] $end
    $var wire 32 @ register_array[24] [31:0] $end
    $var wire 32 A register_array[25] [31:0] $end
    $var wire 32 B register_array[26] [31:0] $end
    $var wire 32 C register_array[27] [31:0] $end
    $var wire 32 D register_array[28] [31:0] $end
    $var wire 32 E register_array[29] [31:0] $end
    $var wire 32 * register_array[2] [31:0] $end
    $var wire 32 F register_array[30] [31:0] $end
    $var wire 32 G register_array[31] [31:0] $end
    $var wire 32 + register_array[3] [31:0] $end
    $var wire 32 , register_array[4] [31:0] $end
    $var wire 32 - register_array[5] [31:0] $end
    $var wire 32 . register_array[6] [31:0] $end
    $var wire 32 / register_array[7] [31:0] $end
    $var wire 32 0 register_array[8] [31:0] $end
    $var wire 32 1 register_array[9] [31:0] $end
   $upscope $end
   $scope module aluCPU $end
    $var wire  3 V ALUctrl [2:0] $end
    $var wire 32 $ ALUop1 [31:0] $end
    $var wire 32 M ALUop2 [31:0] $end
    $var wire 32 I ALUout [31:0] $end
    $var wire  1 K ALUsrc $end
    $var wire 32 \ DATAWIDTH [31:0] $end
    $var wire  1 U Eq $end
    $var wire 32 S ImmOp [31:0] $end
    $var wire 32 T regOp2 [31:0] $end
   $upscope $end
   $scope module control $end
    $var wire  3 V ALUctrl [2:0] $end
    $var wire  1 K ALUsrc $end
    $var wire 32 \ AW [31:0] $end
    $var wire  1 U Eq $end
    $var wire  3 L ImmSrc [2:0] $end
    $var wire  1 H PCsrc $end
    $var wire  1 J RegWrite $end
    $var wire 32 R instr [31:0] $end
    $var wire  7 N opcode [6:0] $end
   $upscope $end
   $scope module extend $end
    $var wire 32 \ DATA_WIDTH [31:0] $end
    $var wire 32 _ IMMSRC_WIDTH [31:0] $end
    $var wire 32 ` imm_length [31:0] $end
    $var wire 32 S immop [31:0] $end
    $var wire  3 L immsrc [2:0] $end
    $var wire 32 R instr [31:0] $end
   $upscope $end
  $upscope $end
 $upscope $end
$enddefinitions $end


#0
b00000000000000000000000000000000 #
b00000000000000000000000000000000 $
b00000000000000000000000000000100 %
b00000000 &
b00000000 '
b00000000000000000000000000000000 (
b00000000000000000000000000000000 )
b00000000000000000000000000000000 *
b00000000000000000000000000000000 +
b00000000000000000000000000000000 ,
b00000000000000000000000000000000 -
b00000000000000000000000000000000 .
b00000000000000000000000000000000 /
b00000000000000000000000000000000 0
b00000000000000000000000000000000 1
b00000000000000000000000000000000 2
b00000000000000000000000000000000 3
b00000000000000000000000000000000 4
b00000000000000000000000000000000 5
b00000000000000000000000000000000 6
b00000000000000000000000000000000 7
b00000000000000000000000000000000 8
b00000000000000000000000000000000 9
b00000000000000000000000000000000 :
b00000000000000000000000000000000 ;
b00000000000000000000000000000000 <
b00000000000000000000000000000000 =
b00000000000000000000000000000000 >
b00000000000000000000000000000000 ?
b00000000000000000000000000000000 @
b00000000000000000000000000000000 A
b00000000000000000000000000000000 B
b00000000000000000000000000000000 C
b00000000000000000000000000000000 D
b00000000000000000000000000000000 E
b00000000000000000000000000000000 F
b00000000000000000000000000000000 G
0H
b00000000000000000000000000000000 I
0J
0K
b000 L
b00000000000000000000000000000000 M
b0000000 N
0O
0P
b00000000000000000000000000000000 Q
b00000000000000000000000000000000 R
b00000000000000000000000000000000 S
b00000000000000000000000000000000 T
1U
b000 V
b00000 W
b00000 X
b00000 Y
b00000000000000000000000000000000 Z
b00000000000000000000000000000100 [
b00000000000000000000000000100000 \
b00000000000000000000000000001000 ]
b00000000000000000000000000000101 ^
b00000000000000000000000000000011 _
b00000000000000000000000000001100 `
#1
b00001111 '
b0001111 N
1O
b00000000000000000000000000001111 R
#2
0O
#3
b00000000000000000000000000000100 #
b00000000000000000000000000001000 %
b00000100 &
b00000000 '
b0000000 N
1O
b00000000000000000000000000000000 R
b00000000000000000000000000000100 Z
b00000000000000000000000000001000 [
#4
0O
#5
b00000000000000000000000000001000 #
b00000000000000000000000000001100 %
b00001000 &
b00001111 '
b0001111 N
1O
b00000000000000000000000000001111 R
b00000000000000000000000000001000 Z
b00000000000000000000000000001100 [
#6
0O
#7
b00000000000000000000000000001100 #
b00000000000000000000000000010000 %
b00001100 &
b00000000 '
b0000000 N
1O
b00000000000000000000000000000000 R
b00000000000000000000000000001100 Z
b00000000000000000000000000010000 [
#8
0O
#9
b00000000000000000000000000010000 #
b00000000000000000000000000010100 %
b00010000 &
1O
b00000000000000000000000000010000 Z
b00000000000000000000000000010100 [
#10
0O
#11
b00000000000000000000000000010100 #
b00000000000000000000000000011000 %
b00010100 &
b11111110 '
b1111110 N
1O
b00000000000000000000000011111110 R
b00001 Y
b00000000000000000000000000010100 Z
b00000000000000000000000000011000 [
#12
0O
#13
b00000000000000000000000000011000 #
b00000000000000000000000000011100 %
b00011000 &
1O
b00000000000000000000000000011000 Z
b00000000000000000000000000011100 [
#14
0O
#15
b00000000000000000000000000011100 #
b00000000000000000000000000100000 %
b00011100 &
b00000000 '
b0000000 N
1O
b00000000000000000000000000000000 R
b00000 Y
b00000000000000000000000000011100 Z
b00000000000000000000000000100000 [
#16
0O
#17
b00000000000000000000000000100000 #
b00000000000000000000000000100100 %
b00100000 &
1O
b00000000000000000000000000100000 Z
b00000000000000000000000000100100 [
#18
0O
#19
b00000000000000000000000000100100 #
b00000000000000000000000000101000 %
b00100100 &
1O
b00000000000000000000000000100100 Z
b00000000000000000000000000101000 [
#20
0O
#21
b00000000000000000000000000101000 #
b00000000000000000000000000101100 %
b00101000 &
1O
b00000000000000000000000000101000 Z
b00000000000000000000000000101100 [
#22
0O
#23
b00000000000000000000000000101100 #
b00000000000000000000000000110000 %
b00101100 &
1O
b00000000000000000000000000101100 Z
b00000000000000000000000000110000 [
#24
0O
#25
b00000000000000000000000000110000 #
b00000000000000000000000000110100 %
b00110000 &
1O
b00000000000000000000000000110000 Z
b00000000000000000000000000110100 [
#26
0O
#27
b00000000000000000000000000110100 #
b00000000000000000000000000111000 %
b00110100 &
1O
b00000000000000000000000000110100 Z
b00000000000000000000000000111000 [
#28
0O
#29
b00000000000000000000000000111000 #
b00000000000000000000000000111100 %
b00111000 &
1O
b00000000000000000000000000111000 Z
b00000000000000000000000000111100 [
#30
0O
#31
b00000000000000000000000000111100 #
b00000000000000000000000001000000 %
b00111100 &
1O
b00000000000000000000000000111100 Z
b00000000000000000000000001000000 [
#32
0O
#33
b00000000000000000000000001000000 #
b00000000000000000000000001000100 %
b01000000 &
1O
b00000000000000000000000001000000 Z
b00000000000000000000000001000100 [
#34
0O
#35
b00000000000000000000000001000100 #
b00000000000000000000000001001000 %
b01000100 &
1O
b00000000000000000000000001000100 Z
b00000000000000000000000001001000 [
#36
0O
#37
b00000000000000000000000001001000 #
b00000000000000000000000001001100 %
b01001000 &
1O
b00000000000000000000000001001000 Z
b00000000000000000000000001001100 [
#38
0O
#39
b00000000000000000000000001001100 #
b00000000000000000000000001010000 %
b01001100 &
1O
b00000000000000000000000001001100 Z
b00000000000000000000000001010000 [
#40
0O
#41
b00000000000000000000000001010000 #
b00000000000000000000000001010100 %
b01010000 &
1O
b00000000000000000000000001010000 Z
b00000000000000000000000001010100 [
#42
0O
#43
b00000000000000000000000001010100 #
b00000000000000000000000001011000 %
b01010100 &
1O
b00000000000000000000000001010100 Z
b00000000000000000000000001011000 [
#44
0O
#45
b00000000000000000000000001011000 #
b00000000000000000000000001011100 %
b01011000 &
1O
b00000000000000000000000001011000 Z
b00000000000000000000000001011100 [
#46
0O
#47
b00000000000000000000000001011100 #
b00000000000000000000000001100000 %
b01011100 &
1O
b00000000000000000000000001011100 Z
b00000000000000000000000001100000 [
#48
0O
#49
b00000000000000000000000001100000 #
b00000000000000000000000001100100 %
b01100000 &
1O
b00000000000000000000000001100000 Z
b00000000000000000000000001100100 [
#50
0O
#51
b00000000000000000000000001100100 #
b00000000000000000000000001101000 %
b01100100 &
1O
b00000000000000000000000001100100 Z
b00000000000000000000000001101000 [
#52
0O
#53
b00000000000000000000000001101000 #
b00000000000000000000000001101100 %
b01101000 &
1O
b00000000000000000000000001101000 Z
b00000000000000000000000001101100 [
#54
0O
#55
b00000000000000000000000001101100 #
b00000000000000000000000001110000 %
b01101100 &
1O
b00000000000000000000000001101100 Z
b00000000000000000000000001110000 [
#56
0O
#57
b00000000000000000000000001110000 #
b00000000000000000000000001110100 %
b01110000 &
1O
b00000000000000000000000001110000 Z
b00000000000000000000000001110100 [
#58
0O
#59
b00000000000000000000000001110100 #
b00000000000000000000000001111000 %
b01110100 &
1O
b00000000000000000000000001110100 Z
b00000000000000000000000001111000 [
#60
0O
#61
b00000000000000000000000001111000 #
b00000000000000000000000001111100 %
b01111000 &
1O
b00000000000000000000000001111000 Z
b00000000000000000000000001111100 [
#62
0O
#63
b00000000000000000000000001111100 #
b00000000000000000000000010000000 %
b01111100 &
1O
b00000000000000000000000001111100 Z
b00000000000000000000000010000000 [
#64
0O
#65
b00000000000000000000000010000000 #
b00000000000000000000000010000100 %
b10000000 &
1O
b00000000000000000000000010000000 Z
b00000000000000000000000010000100 [
#66
0O
#67
b00000000000000000000000010000100 #
b00000000000000000000000010001000 %
b10000100 &
1O
b00000000000000000000000010000100 Z
b00000000000000000000000010001000 [
#68
0O
#69
b00000000000000000000000010001000 #
b00000000000000000000000010001100 %
b10001000 &
1O
b00000000000000000000000010001000 Z
b00000000000000000000000010001100 [
#70
0O
#71
b00000000000000000000000010001100 #
b00000000000000000000000010010000 %
b10001100 &
1O
b00000000000000000000000010001100 Z
b00000000000000000000000010010000 [
#72
0O
#73
b00000000000000000000000010010000 #
b00000000000000000000000010010100 %
b10010000 &
1O
b00000000000000000000000010010000 Z
b00000000000000000000000010010100 [
#74
0O
#75
b00000000000000000000000010010100 #
b00000000000000000000000010011000 %
b10010100 &
1O
b00000000000000000000000010010100 Z
b00000000000000000000000010011000 [
#76
0O
#77
b00000000000000000000000010011000 #
b00000000000000000000000010011100 %
b10011000 &
1O
b00000000000000000000000010011000 Z
b00000000000000000000000010011100 [
#78
0O
#79
b00000000000000000000000010011100 #
b00000000000000000000000010100000 %
b10011100 &
1O
b00000000000000000000000010011100 Z
b00000000000000000000000010100000 [
#80
0O
#81
b00000000000000000000000010100000 #
b00000000000000000000000010100100 %
b10100000 &
1O
b00000000000000000000000010100000 Z
b00000000000000000000000010100100 [
#82
0O
#83
b00000000000000000000000010100100 #
b00000000000000000000000010101000 %
b10100100 &
1O
b00000000000000000000000010100100 Z
b00000000000000000000000010101000 [
#84
0O
#85
b00000000000000000000000010101000 #
b00000000000000000000000010101100 %
b10101000 &
1O
b00000000000000000000000010101000 Z
b00000000000000000000000010101100 [
#86
0O
#87
b00000000000000000000000010101100 #
b00000000000000000000000010110000 %
b10101100 &
1O
b00000000000000000000000010101100 Z
b00000000000000000000000010110000 [
#88
0O
#89
b00000000000000000000000010110000 #
b00000000000000000000000010110100 %
b10110000 &
1O
b00000000000000000000000010110000 Z
b00000000000000000000000010110100 [
#90
0O
#91
b00000000000000000000000010110100 #
b00000000000000000000000010111000 %
b10110100 &
1O
b00000000000000000000000010110100 Z
b00000000000000000000000010111000 [
#92
0O
#93
b00000000000000000000000010111000 #
b00000000000000000000000010111100 %
b10111000 &
1O
b00000000000000000000000010111000 Z
b00000000000000000000000010111100 [
#94
0O
#95
b00000000000000000000000010111100 #
b00000000000000000000000011000000 %
b10111100 &
1O
b00000000000000000000000010111100 Z
b00000000000000000000000011000000 [
#96
0O
#97
b00000000000000000000000011000000 #
b00000000000000000000000011000100 %
b11000000 &
1O
b00000000000000000000000011000000 Z
b00000000000000000000000011000100 [
#98
0O
#99
b00000000000000000000000011000100 #
b00000000000000000000000011001000 %
b11000100 &
1O
b00000000000000000000000011000100 Z
b00000000000000000000000011001000 [
#100
0O
#101
b00000000000000000000000011001000 #
b00000000000000000000000011001100 %
b11001000 &
1O
b00000000000000000000000011001000 Z
b00000000000000000000000011001100 [
#102
0O
#103
b00000000000000000000000011001100 #
b00000000000000000000000011010000 %
b11001100 &
1O
b00000000000000000000000011001100 Z
b00000000000000000000000011010000 [
#104
0O
#105
b00000000000000000000000011010000 #
b00000000000000000000000011010100 %
b11010000 &
1O
b00000000000000000000000011010000 Z
b00000000000000000000000011010100 [
#106
0O
#107
b00000000000000000000000011010100 #
b00000000000000000000000011011000 %
b11010100 &
1O
b00000000000000000000000011010100 Z
b00000000000000000000000011011000 [
#108
0O
#109
b00000000000000000000000011011000 #
b00000000000000000000000011011100 %
b11011000 &
1O
b00000000000000000000000011011000 Z
b00000000000000000000000011011100 [
#110
0O
#111
b00000000000000000000000011011100 #
b00000000000000000000000011100000 %
b11011100 &
1O
b00000000000000000000000011011100 Z
b00000000000000000000000011100000 [
#112
0O
#113
b00000000000000000000000011100000 #
b00000000000000000000000011100100 %
b11100000 &
1O
b00000000000000000000000011100000 Z
b00000000000000000000000011100100 [
#114
0O
#115
b00000000000000000000000011100100 #
b00000000000000000000000011101000 %
b11100100 &
1O
b00000000000000000000000011100100 Z
b00000000000000000000000011101000 [
#116
0O
#117
b00000000000000000000000011101000 #
b00000000000000000000000011101100 %
b11101000 &
1O
b00000000000000000000000011101000 Z
b00000000000000000000000011101100 [
#118
0O
#119
b00000000000000000000000011101100 #
b00000000000000000000000011110000 %
b11101100 &
1O
b00000000000000000000000011101100 Z
b00000000000000000000000011110000 [
#120
0O
#121
b00000000000000000000000011110000 #
b00000000000000000000000011110100 %
b11110000 &
1O
b00000000000000000000000011110000 Z
b00000000000000000000000011110100 [
#122
0O
#123
b00000000000000000000000011110100 #
b00000000000000000000000011111000 %
b11110100 &
1O
b00000000000000000000000011110100 Z
b00000000000000000000000011111000 [
#124
0O
#125
b00000000000000000000000011111000 #
b00000000000000000000000011111100 %
b11111000 &
1O
b00000000000000000000000011111000 Z
b00000000000000000000000011111100 [
#126
0O
#127
b00000000000000000000000011111100 #
b00000000000000000000000100000000 %
b11111100 &
1O
b00000000000000000000000011111100 Z
b00000000000000000000000100000000 [
#128
0O
#129
b00000000000000000000000100000000 #
b00000000000000000000000100000100 %
b00000000 &
b00001111 '
b0001111 N
1O
b00000000000000000000000000001111 R
b00000000000000000000000100000000 Z
b00000000000000000000000100000100 [
#130
0O
#131
b00000000000000000000000100000100 #
b00000000000000000000000100001000 %
b00000100 &
b00000000 '
b0000000 N
1O
b00000000000000000000000000000000 R
b00000000000000000000000100000100 Z
b00000000000000000000000100001000 [
#132
0O
#133
b00000000000000000000000100001000 #
b00000000000000000000000100001100 %
b00001000 &
b00001111 '
b0001111 N
1O
b00000000000000000000000000001111 R
b00000000000000000000000100001000 Z
b00000000000000000000000100001100 [
#134
0O
#135
b00000000000000000000000100001100 #
b00000000000000000000000100010000 %
b00001100 &
b00000000 '
b0000000 N
1O
b00000000000000000000000000000000 R
b00000000000000000000000100001100 Z
b00000000000000000000000100010000 [
#136
0O
#137
b00000000000000000000000100010000 #
b00000000000000000000000100010100 %
b00010000 &
1O
b00000000000000000000000100010000 Z
b00000000000000000000000100010100 [
#138
0O
#139
b00000000000000000000000100010100 #
b00000000000000000000000100011000 %
b00010100 &
b11111110 '
b1111110 N
1O
b00000000000000000000000011111110 R
b00001 Y
b00000000000000000000000100010100 Z
b00000000000000000000000100011000 [
#140
0O
#141
b00000000000000000000000100011000 #
b00000000000000000000000100011100 %
b00011000 &
1O
b00000000000000000000000100011000 Z
b00000000000000000000000100011100 [
#142
0O
#143
b00000000000000000000000100011100 #
b00000000000000000000000100100000 %
b00011100 &
b00000000 '
b0000000 N
1O
b00000000000000000000000000000000 R
b00000 Y
b00000000000000000000000100011100 Z
b00000000000000000000000100100000 [
#144
0O
#145
b00000000000000000000000100100000 #
b00000000000000000000000100100100 %
b00100000 &
1O
b00000000000000000000000100100000 Z
b00000000000000000000000100100100 [
#146
0O
#147
b00000000000000000000000100100100 #
b00000000000000000000000100101000 %
b00100100 &
1O
b00000000000000000000000100100100 Z
b00000000000000000000000100101000 [
#148
0O
#149
b00000000000000000000000100101000 #
b00000000000000000000000100101100 %
b00101000 &
1O
b00000000000000000000000100101000 Z
b00000000000000000000000100101100 [
#150
0O
#151
b00000000000000000000000100101100 #
b00000000000000000000000100110000 %
b00101100 &
1O
b00000000000000000000000100101100 Z
b00000000000000000000000100110000 [
#152
0O
#153
b00000000000000000000000100110000 #
b00000000000000000000000100110100 %
b00110000 &
1O
b00000000000000000000000100110000 Z
b00000000000000000000000100110100 [
#154
0O
#155
b00000000000000000000000100110100 #
b00000000000000000000000100111000 %
b00110100 &
1O
b00000000000000000000000100110100 Z
b00000000000000000000000100111000 [
#156
0O
#157
b00000000000000000000000100111000 #
b00000000000000000000000100111100 %
b00111000 &
1O
b00000000000000000000000100111000 Z
b00000000000000000000000100111100 [
#158
0O
#159
b00000000000000000000000100111100 #
b00000000000000000000000101000000 %
b00111100 &
1O
b00000000000000000000000100111100 Z
b00000000000000000000000101000000 [
#160
0O
#161
b00000000000000000000000101000000 #
b00000000000000000000000101000100 %
b01000000 &
1O
b00000000000000000000000101000000 Z
b00000000000000000000000101000100 [
#162
0O
#163
b00000000000000000000000101000100 #
b00000000000000000000000101001000 %
b01000100 &
1O
b00000000000000000000000101000100 Z
b00000000000000000000000101001000 [
#164
0O
#165
b00000000000000000000000101001000 #
b00000000000000000000000101001100 %
b01001000 &
1O
b00000000000000000000000101001000 Z
b00000000000000000000000101001100 [
#166
0O
#167
b00000000000000000000000101001100 #
b00000000000000000000000101010000 %
b01001100 &
1O
b00000000000000000000000101001100 Z
b00000000000000000000000101010000 [
#168
0O
#169
b00000000000000000000000101010000 #
b00000000000000000000000101010100 %
b01010000 &
1O
b00000000000000000000000101010000 Z
b00000000000000000000000101010100 [
#170
0O
#171
b00000000000000000000000101010100 #
b00000000000000000000000101011000 %
b01010100 &
1O
b00000000000000000000000101010100 Z
b00000000000000000000000101011000 [
#172
0O
#173
b00000000000000000000000101011000 #
b00000000000000000000000101011100 %
b01011000 &
1O
b00000000000000000000000101011000 Z
b00000000000000000000000101011100 [
#174
0O
#175
b00000000000000000000000101011100 #
b00000000000000000000000101100000 %
b01011100 &
1O
b00000000000000000000000101011100 Z
b00000000000000000000000101100000 [
#176
0O
#177
b00000000000000000000000101100000 #
b00000000000000000000000101100100 %
b01100000 &
1O
b00000000000000000000000101100000 Z
b00000000000000000000000101100100 [
#178
0O
#179
b00000000000000000000000101100100 #
b00000000000000000000000101101000 %
b01100100 &
1O
b00000000000000000000000101100100 Z
b00000000000000000000000101101000 [
#180
0O
#181
b00000000000000000000000101101000 #
b00000000000000000000000101101100 %
b01101000 &
1O
b00000000000000000000000101101000 Z
b00000000000000000000000101101100 [
#182
0O
#183
b00000000000000000000000101101100 #
b00000000000000000000000101110000 %
b01101100 &
1O
b00000000000000000000000101101100 Z
b00000000000000000000000101110000 [
#184
0O
#185
b00000000000000000000000101110000 #
b00000000000000000000000101110100 %
b01110000 &
1O
b00000000000000000000000101110000 Z
b00000000000000000000000101110100 [
#186
0O
#187
b00000000000000000000000101110100 #
b00000000000000000000000101111000 %
b01110100 &
1O
b00000000000000000000000101110100 Z
b00000000000000000000000101111000 [
#188
0O
#189
b00000000000000000000000101111000 #
b00000000000000000000000101111100 %
b01111000 &
1O
b00000000000000000000000101111000 Z
b00000000000000000000000101111100 [
#190
0O
#191
b00000000000000000000000101111100 #
b00000000000000000000000110000000 %
b01111100 &
1O
b00000000000000000000000101111100 Z
b00000000000000000000000110000000 [
#192
0O
#193
b00000000000000000000000110000000 #
b00000000000000000000000110000100 %
b10000000 &
1O
b00000000000000000000000110000000 Z
b00000000000000000000000110000100 [
#194
0O
