ALU.sv
module ALU #(
    parameter DATAWIDTH = 32
)(
    input logic [DATAWIDTH-1:0]         ALUop1,
    input logic [2:0]                   ALUctrl,
    input logic                         ALUsrc,
    input logic [DATAWIDTH-1:0]         regOp2,
    input logic [DATAWIDTH-1:0]         ImmOp,
    // input logic clk,

    output logic [DATAWIDTH-1:0]        ALUout,
    output logic Eq
);

    logic [DATAWIDTH-1:0] ALUop2;
     
always_comb begin
    ALUop2 = ALUsrc ? ImmOp : regOp2;
    case (ALUctrl)
        3'b000: ALUout = ALUop1 + ALUop2;
        3'b001: ALUout= 32'b0;
        3'b010: ALUout= 32'b0;
        3'b011: ALUout= 32'b0;
        3'b100: ALUout= 32'b0;
        3'b101: ALUout= 32'b0;
        3'b110: ALUout= 32'b0;
        default: ALUout = 0;
    endcase
    
end
assign Eq = (ALUop1==ALUop2);
// always_ff @(posedge clk) begin
//     $display("aluop1: ",ALUop1);
//     $display("aluop2: ",ALUop2);
//     $display("eq : ",Eq);
// end


endmodule

signextendo.sv
module signextendo #(
    DW=32
) (
    input logic[2:0] ImmSrc,
    input logic [DW-1:0] instr,
    output logic [DW-1:0] ImmOp
);
    logic [11:0] immediate;
    logic msb;
    always_comb begin
        case (ImmSrc)
        3'b000:begin //imm in bit[31:20] of inst
            immediate=instr[31:20];
            msb=immediate[11];
            ImmOp={{5'd20{msb}},{immediate[11:0]}};
        end
        3'b001:begin
            immediate={instr[31],instr[7],instr[30:25],instr[11:8]};
            msb=immediate[11];
            ImmOp={{5'd20{msb}},{immediate[11:0]}};
        end
        default:begin
            ImmOp=0;
        end
        endcase
    end
    
endmodule

register_file.sv
module register_file #(
    parameter ADDRESS_WIDTH = 5,
                DATA_WIDTH = 32
)(
    input logic                             clk,
    input logic [ADDRESS_WIDTH-1:0]         AD1,
    input logic [ADDRESS_WIDTH-1:0]         AD2,
    input logic [ADDRESS_WIDTH-1:0]         AD3,
    input logic                             WE3,
    input logic [DATA_WIDTH-1:0]            WD3,

    output logic [DATA_WIDTH-1:0]           RD1,
    output logic [DATA_WIDTH-1:0]           RD2,
    output logic [DATA_WIDTH-1:0]           a0  
);

//connecting mux logic: ALUsrc ? ImmOp : regOp2;

logic [DATA_WIDTH-1:0] register_array [2**ADDRESS_WIDTH-1:0];

initial begin
    for (int i = 0; i < $size(register_array); i++) begin
        register_array[i] = 32'b0;
    end
end
always_ff @(posedge clk) begin
    if (WE3) register_array[AD3] <= WD3;
   
end
always_comb begin
   
    RD1 = register_array[AD1];
    RD2 = register_array[AD2];
end
assign  a0 = register_array[10];

endmodule

control.sv
module control #(
    parameter AW=32
) (
    input logic Eq,
    input logic [AW-1:0] instr,
    output logic RegWrite,
    output logic [2:0] ALUctrl,
    output logic ALUsrc,
    output logic [2:0] ImmSrc,
    output logic PCsrc 
);
    logic [6:0] opcode;
    
    always_comb begin
        opcode=instr[6:0];
        ALUctrl=instr[14:12];
        // ALUsrc=instr[5]? 0: 1;
        case (opcode)
            7'd19: begin //store inst
                 ImmSrc=3'b000;
                 RegWrite=1'b1;
                 PCsrc=1'b0;
                 ALUsrc=1'b1;
                end
            7'd99:begin //jump instr
                ImmSrc=3'b001;
                RegWrite=1'b0;
                PCsrc=Eq?1'b0:1'b1;
                ALUsrc=1'b0;
            end
         default: begin
            ImmSrc=3'b000;
            RegWrite=1'b0;
            PCsrc=1'b0;
        end          
        endcase

    end
endmodule

ROM.sv
module ROM #(
    parameter DATA_WIDTH = 32
)(
    input logic [DATA_WIDTH-1:0]   A,
    output logic [DATA_WIDTH-1:0]  dout1
);

logic [7:0] rom_array [30:0];

initial begin
    $display("Loading rom.");
    $readmemh("example_rom.mem", rom_array);
    $display("done loading rom.");
    $display(rom_array[27]);
end

always_comb begin
    //output is asynchronous
    assign dout1 = {{rom_array[A]}, {rom_array[A+1]}, {rom_array[A+2]}, {rom_array[A+3]}}; 
end
endmodule

PC.sv
module PC #(
    DW=32

) (
    input logic     clk,
    input logic     rst,
    input logic     PCsrc,
    input logic   [DW-1:0]  ImmOp,
    output logic  [DW-1:0]  PCC
);
    
    logic [DW-1:0] inc_PC;
    logic [DW-1:0] branch_PC;
    logic [DW-1:0] next_PC;

    assign branch_PC = PCC+ImmOp;
    assign inc_PC=PCC+4;
    assign next_PC=PCsrc ? branch_PC : inc_PC;
   
    always_comb begin
        
    end

    always_ff @(posedge clk ) begin
        // $display("PC= ",PCC);
        if (rst) PCC<=32'b0;
        else PCC<=next_PC;
    end

endmodule

top.sv
module top #(
    parameter DW=32
) (
    input logic clk,
    input logic rst,
    output logic [DW-1:0] a0out,
    output logic [DW-1:0] InstructionWire,
    output logic [DW-1:0] ImmOpWire 
);

    logic PCsrsWire;
    
    logic [DW-1:0] PCWire;
    
    logic [DW-1:0] ALUoutWire;
    logic [DW-1:0] RD1Wire;
    logic [DW-1:0] RD2Wire;
    logic EQWire;
    logic RegWriteWire;
    logic ALUsrcWire;
    logic [2:0] ALUctrlWire;
    logic [2:0] ImmSrcWire;
    logic [4:0] rs1;
    logic [4:0] rs2;
    logic [4:0] rd;
    
    PC PC(
        .clk(clk),
        .rst(rst),
        .PCsrc(PCsrsWire),
        .ImmOp(ImmOpWire),
        .PCC(PCWire)
    );
    
    ROM ROM(
        .A(PCWire),
        
        .dout1(InstructionWire)
    );
   
    assign rs1 = InstructionWire[19:15];
    assign rs2 = InstructionWire[24:20];
    assign rd = InstructionWire[11:7];
    
    control control(
        .Eq(EQWire),
        .instr(InstructionWire),
        .RegWrite(RegWriteWire),
        .ALUctrl(ALUctrlWire),
        .ALUsrc(ALUsrcWire),
        .ImmSrc(ImmSrcWire),
        .PCsrc(PCsrsWire)
    );

    register_file RegFile(
        .clk(clk),
        .AD1(rs1),
        .AD2(rs2),
        .AD3(rd),
        .WE3(RegWriteWire),
        .WD3(ALUoutWire),

        .a0(a0out),
        .RD1(RD1Wire),
        .RD2(RD2Wire)
    );
    signextendo extendo(
        .instr(InstructionWire),
        .ImmSrc(ImmSrcWire),

        .ImmOp(ImmOpWire)
    );
    ALU aluCPU(
        .ALUop1(RD1Wire),
        .ALUctrl(ALUctrlWire),
        .ALUsrc(ALUsrcWire),
        .regOp2(RD2Wire), //register
        .ImmOp(ImmOpWire), //immediate comparison done inside alu

        .ALUout(ALUoutWire),
        .Eq(EQWire)
    );
    

    
endmodule

top.vcd
$version Generated by VerilatedVcd $end
$date Mon Nov 21 19:53:59 2022 $end
$timescale 1ps $end

 $scope module TOP $end
  $var wire 32 s ImmOpWire [31:0] $end
  $var wire 32 r InstructionWire [31:0] $end
  $var wire 32 q a0out [31:0] $end
  $var wire  1 o clk $end
  $var wire  1 p rst $end
  $scope module top $end
   $var wire  3 v ALUctrlWire [2:0] $end
   $var wire 32 g ALUoutWire [31:0] $end
   $var wire  1 i ALUsrcWire $end
   $var wire 32 | DW [31:0] $end
   $var wire  1 u EQWire $end
   $var wire 32 s ImmOpWire [31:0] $end
   $var wire  3 j ImmSrcWire [2:0] $end
   $var wire 32 r InstructionWire [31:0] $end
   $var wire 32 C PCWire [31:0] $end
   $var wire  1 f PCsrsWire $end
   $var wire 32 D RD1Wire [31:0] $end
   $var wire 32 t RD2Wire [31:0] $end
   $var wire  1 h RegWriteWire $end
   $var wire 32 q a0out [31:0] $end
   $var wire  1 o clk $end
   $var wire  5 y rd [4:0] $end
   $var wire  5 w rs1 [4:0] $end
   $var wire  5 x rs2 [4:0] $end
   $var wire  1 p rst $end
   $scope module PC $end
    $var wire 32 | DW [31:0] $end
    $var wire 32 s ImmOp [31:0] $end
    $var wire 32 C PCC [31:0] $end
    $var wire  1 f PCsrc $end
    $var wire 32 z branch_PC [31:0] $end
    $var wire  1 o clk $end
    $var wire 32 E inc_PC [31:0] $end
    $var wire 32 { next_PC [31:0] $end
    $var wire  1 p rst $end
   $upscope $end
   $scope module ROM $end
    $var wire 32 C A [31:0] $end
    $var wire 32 | DATA_WIDTH [31:0] $end
    $var wire 32 r dout1 [31:0] $end
    $var wire  8 # rom_array[0] [7:0] $end
    $var wire  8 - rom_array[10] [7:0] $end
    $var wire  8 . rom_array[11] [7:0] $end
    $var wire  8 / rom_array[12] [7:0] $end
    $var wire  8 0 rom_array[13] [7:0] $end
    $var wire  8 1 rom_array[14] [7:0] $end
    $var wire  8 2 rom_array[15] [7:0] $end
    $var wire  8 3 rom_array[16] [7:0] $end
    $var wire  8 4 rom_array[17] [7:0] $end
    $var wire  8 5 rom_array[18] [7:0] $end
    $var wire  8 6 rom_array[19] [7:0] $end
    $var wire  8 $ rom_array[1] [7:0] $end
    $var wire  8 7 rom_array[20] [7:0] $end
    $var wire  8 8 rom_array[21] [7:0] $end
    $var wire  8 9 rom_array[22] [7:0] $end
    $var wire  8 : rom_array[23] [7:0] $end
    $var wire  8 ; rom_array[24] [7:0] $end
    $var wire  8 < rom_array[25] [7:0] $end
    $var wire  8 = rom_array[26] [7:0] $end
    $var wire  8 > rom_array[27] [7:0] $end
    $var wire  8 ? rom_array[28] [7:0] $end
    $var wire  8 @ rom_array[29] [7:0] $end
    $var wire  8 % rom_array[2] [7:0] $end
    $var wire  8 A rom_array[30] [7:0] $end
    $var wire  8 & rom_array[3] [7:0] $end
    $var wire  8 ' rom_array[4] [7:0] $end
    $var wire  8 ( rom_array[5] [7:0] $end
    $var wire  8 ) rom_array[6] [7:0] $end
    $var wire  8 * rom_array[7] [7:0] $end
    $var wire  8 + rom_array[8] [7:0] $end
    $var wire  8 , rom_array[9] [7:0] $end
   $upscope $end
   $scope module RegFile $end
    $var wire  5 w AD1 [4:0] $end
    $var wire  5 x AD2 [4:0] $end
    $var wire  5 y AD3 [4:0] $end
    $var wire 32 } ADDRESS_WIDTH [31:0] $end
    $var wire 32 | DATA_WIDTH [31:0] $end
    $var wire 32 D RD1 [31:0] $end
    $var wire 32 t RD2 [31:0] $end
    $var wire 32 g WD3 [31:0] $end
    $var wire  1 h WE3 $end
    $var wire 32 q a0 [31:0] $end
    $var wire  1 o clk $end
    $var wire 32 F register_array[0] [31:0] $end
    $var wire 32 P register_array[10] [31:0] $end
    $var wire 32 Q register_array[11] [31:0] $end
    $var wire 32 R register_array[12] [31:0] $end
    $var wire 32 S register_array[13] [31:0] $end
    $var wire 32 T register_array[14] [31:0] $end
    $var wire 32 U register_array[15] [31:0] $end
    $var wire 32 V register_array[16] [31:0] $end
    $var wire 32 W register_array[17] [31:0] $end
    $var wire 32 X register_array[18] [31:0] $end
    $var wire 32 Y register_array[19] [31:0] $end
    $var wire 32 G register_array[1] [31:0] $end
    $var wire 32 Z register_array[20] [31:0] $end
    $var wire 32 [ register_array[21] [31:0] $end
    $var wire 32 \ register_array[22] [31:0] $end
    $var wire 32 ] register_array[23] [31:0] $end
    $var wire 32 ^ register_array[24] [31:0] $end
    $var wire 32 _ register_array[25] [31:0] $end
    $var wire 32 ` register_array[26] [31:0] $end
    $var wire 32 a register_array[27] [31:0] $end
    $var wire 32 b register_array[28] [31:0] $end
    $var wire 32 c register_array[29] [31:0] $end
    $var wire 32 H register_array[2] [31:0] $end
    $var wire 32 d register_array[30] [31:0] $end
    $var wire 32 e register_array[31] [31:0] $end
    $var wire 32 I register_array[3] [31:0] $end
    $var wire 32 J register_array[4] [31:0] $end
    $var wire 32 K register_array[5] [31:0] $end
    $var wire 32 L register_array[6] [31:0] $end
    $var wire 32 M register_array[7] [31:0] $end
    $var wire 32 N register_array[8] [31:0] $end
    $var wire 32 O register_array[9] [31:0] $end
    $scope module unnamedblk1 $end
     $var wire 32 B i [31:0] $end
    $upscope $end
   $upscope $end
   $scope module aluCPU $end
    $var wire  3 v ALUctrl [2:0] $end
    $var wire 32 D ALUop1 [31:0] $end
    $var wire 32 k ALUop2 [31:0] $end
    $var wire 32 g ALUout [31:0] $end
    $var wire  1 i ALUsrc $end
    $var wire 32 | DATAWIDTH [31:0] $end
    $var wire  1 u Eq $end
    $var wire 32 s ImmOp [31:0] $end
    $var wire 32 t regOp2 [31:0] $end
   $upscope $end
   $scope module control $end
    $var wire  3 v ALUctrl [2:0] $end
    $var wire  1 i ALUsrc $end
    $var wire 32 | AW [31:0] $end
    $var wire  1 u Eq $end
    $var wire  3 j ImmSrc [2:0] $end
    $var wire  1 f PCsrc $end
    $var wire  1 h RegWrite $end
    $var wire 32 r instr [31:0] $end
    $var wire  7 l opcode [6:0] $end
   $upscope $end
   $scope module extendo $end
    $var wire 32 | DW [31:0] $end
    $var wire 32 s ImmOp [31:0] $end
    $var wire  3 j ImmSrc [2:0] $end
    $var wire 12 m immediate [11:0] $end
    $var wire 32 r instr [31:0] $end
    $var wire  1 n msb $end
   $upscope $end
  $upscope $end
 $upscope $end
$enddefinitions $end


#54
b00000000 #
b00000000 $
b00000000 %
b00000000 &
b00000000 '
b00000000 (
b00000000 )
b00000000 *
b00000000 +
b00000000 ,
b00000000 -
b00000000 .
b00000000 /
b00000000 0
b00000000 1
b00000000 2
b00000000 3
b00000000 4
b00000000 5
b00000000 6
b00000000 7
b00000000 8
b00000000 9
b00000000 :
b00000000 ;
b00000000 <
b00000000 =
b00000000 >
b00000000 ?
b00000000 @
b00000000 A
b00000000000000000000000000000000 B
b00000000000000000000000000000000 C
b00000000000000000000000000000000 D
b00000000000000000000000000000100 E
b00000000000000000000000000000000 F
b00000000000000000000000000000000 G
b00000000000000000000000000000000 H
b00000000000000000000000000000000 I
b00000000000000000000000000000000 J
b00000000000000000000000000000000 K
b00000000000000000000000000000000 L
b00000000000000000000000000000000 M
b00000000000000000000000000000000 N
b00000000000000000000000000000000 O
b00000000000000000000000000000000 P
b00000000000000000000000000000000 Q
b00000000000000000000000000000000 R
b00000000000000000000000000000000 S
b00000000000000000000000000000000 T
b00000000000000000000000000000000 U
b00000000000000000000000000000000 V
b00000000000000000000000000000000 W
b00000000000000000000000000000000 X
b00000000000000000000000000000000 Y
b00000000000000000000000000000000 Z
b00000000000000000000000000000000 [
b00000000000000000000000000000000 \
b00000000000000000000000000000000 ]
b00000000000000000000000000000000 ^
b00000000000000000000000000000000 _
b00000000000000000000000000000000 `
b00000000000000000000000000000000 a
b00000000000000000000000000000000 b
b00000000000000000000000000000000 c
b00000000000000000000000000000000 d
b00000000000000000000000000000000 e
0f
b00000000000000000000000000000000 g
0h
0i
b000 j
b00000000000000000000000000000000 k
b0000000 l
b000000000000 m
0n
0o
0p
b00000000000000000000000000000000 q
b00000000000000000000000000000000 r
b00000000000000000000000000000000 s
b00000000000000000000000000000000 t
1u
b000 v
b00000 w
b00000 x
b00000 y
b00000000000000000000000000000000 z
b00000000000000000000000000000100 {
b00000000000000000000000000100000 |
b00000000000000000000000000000101 }
#55
b00001111 #
b11110000 $
b00000011 %
b00010011 &
b00000101 )
b00010011 *
b00001111 +
b00000101 -
b10010011 .
b00000101 0
b10000101 1
b00010011 2
b00010101 4
b10000101 5
b10010011 6
b11111110 7
b01100101 8
b10011000 9
b11100011 :
b11111110 ;
b00000011 <
b00010000 =
b00000000000000000000000000100000 B
b00000000000000000000000011111111 g
1h
1i
b00000000000000000000000011111111 k
b0010011 l
b000011111111 m
1o
b00001111111100000000001100010011 r
b00000000000000000000000011111111 s
0u
b11111 x
b00110 y
b00000000000000000000000011111111 z
#56
0o
#57
b00000000000000000000000000000100 C
b00000000000000000000000000001000 E
b00000000000000000000000011111111 L
b00000000000000000000000000000000 g
b00000000000000000000000000000000 k
b000000000000 m
1o
b00000000000000000000010100010011 r
b00000000000000000000000000000000 s
1u
b00000 x
b01010 y
b00000000000000000000000000000100 z
b00000000000000000000000000001000 {
#58
0o
#59
b00000000000000000000000000001000 C
b00000000000000000000000000001100 E
b00000000000000000000000011110000 g
b00000000000000000000000011110000 k
b000011110000 m
1o
b00001111000000000000010110010011 r
b00000000000000000000000011110000 s
0u
b10000 x
b01011 y
b00000000000000000000000011111000 z
b00000000000000000000000000001100 {
#60
0o
#61
b00000000000000000000000000001100 C
b00000000000000000000000011110000 D
b00000000000000000000000000010000 E
b00000000000000000000000011110000 Q
b00000000000000000000000000000000 k
b000000000000 m
1o
b00000000000001011000010100010011 r
b00000000000000000000000000000000 s
b01011 w
b00000 x
b01010 y
b00000000000000000000000000001100 z
b00000000000000000000000000010000 {
#62
0o
#63
b00000000000000000000000000010000 C
b00000000000000000000000000010100 E
b00000000000000000000000011110000 P
b00000000000000000000000011110001 g
b00000000000000000000000000000001 k
b000000000001 m
1o
b00000000000000000000000011110000 q
b00000000000101011000010110010011 r
b00000000000000000000000000000001 s
b00001 x
b01011 y
b00000000000000000000000000010001 z
b00000000000000000000000000010100 {
#64
0o
#65
b00000000000000000000000000010100 C
b00000000000000000000000011110001 D
b00000000000000000000000000011000 E
b00000000000000000000000011110001 Q
1f
b00000000000000000000000000000000 g
0h
0i
b001 j
b00000000000000000000000011111111 k
b1100011 l
b111111111000 m
1n
1o
b11111110011001011001100011100011 r
b11111111111111111111111111111000 s
b00000000000000000000000011111111 t
b001 v
b00110 x
b10001 y
b00000000000000000000000000001100 z
b00000000000000000000000000001100 {
#66
0o
#67
b00000000000000000000000000001100 C
b00000000000000000000000000010000 E
0f
b00000000000000000000000011110001 g
1h
1i
b000 j
b00000000000000000000000000000000 k
b0010011 l
b000000000000 m
0n
1o
b00000000000001011000010100010011 r
b00000000000000000000000000000000 s
b00000000000000000000000000000000 t
b000 v
b00000 x
b01010 y
b00000000000000000000000000010000 {
#68
0o
#69
b00000000000000000000000000010000 C
b00000000000000000000000000010100 E
b00000000000000000000000011110001 P
b00000000000000000000000011110010 g
b00000000000000000000000000000001 k
b000000000001 m
1o
b00000000000000000000000011110001 q
b00000000000101011000010110010011 r
b00000000000000000000000000000001 s
b00001 x
b01011 y
b00000000000000000000000000010001 z
b00000000000000000000000000010100 {
#70
0o
#71
b00000000000000000000000000010100 C
b00000000000000000000000011110010 D
b00000000000000000000000000011000 E
b00000000000000000000000011110010 Q
1f
b00000000000000000000000000000000 g
0h
0i
b001 j
b00000000000000000000000011111111 k
b1100011 l
b111111111000 m
1n
1o
b11111110011001011001100011100011 r
b11111111111111111111111111111000 s
b00000000000000000000000011111111 t
b001 v
b00110 x
b10001 y
b00000000000000000000000000001100 z
b00000000000000000000000000001100 {
#72
0o
#73
b00000000000000000000000000001100 C
b00000000000000000000000000010000 E
0f
b00000000000000000000000011110010 g
1h
1i
b000 j
b00000000000000000000000000000000 k
b0010011 l
b000000000000 m
0n
1o
b00000000000001011000010100010011 r
b00000000000000000000000000000000 s
b00000000000000000000000000000000 t
b000 v
b00000 x
b01010 y
b00000000000000000000000000010000 {
#74
0o
#75
b00000000000000000000000000010000 C
b00000000000000000000000000010100 E
b00000000000000000000000011110010 P
b00000000000000000000000011110011 g
b00000000000000000000000000000001 k
b000000000001 m
1o
b00000000000000000000000011110010 q
b00000000000101011000010110010011 r
b00000000000000000000000000000001 s
b00001 x
b01011 y
b00000000000000000000000000010001 z
b00000000000000000000000000010100 {
#76
0o
#77
b00000000000000000000000000010100 C
b00000000000000000000000011110011 D
b00000000000000000000000000011000 E
b00000000000000000000000011110011 Q
1f
b00000000000000000000000000000000 g
0h
0i
b001 j
b00000000000000000000000011111111 k
b1100011 l
b111111111000 m
1n
1o
b11111110011001011001100011100011 r
b11111111111111111111111111111000 s
b00000000000000000000000011111111 t
b001 v
b00110 x
b10001 y
b00000000000000000000000000001100 z
b00000000000000000000000000001100 {
#78
0o
#79
b00000000000000000000000000001100 C
b00000000000000000000000000010000 E
0f
b00000000000000000000000011110011 g
1h
1i
b000 j
b00000000000000000000000000000000 k
b0010011 l
b000000000000 m
0n
1o
b00000000000001011000010100010011 r
b00000000000000000000000000000000 s
b00000000000000000000000000000000 t
b000 v
b00000 x
b01010 y
b00000000000000000000000000010000 {
#80
0o
#81
b00000000000000000000000000010000 C
b00000000000000000000000000010100 E
b00000000000000000000000011110011 P
b00000000000000000000000011110100 g
b00000000000000000000000000000001 k
b000000000001 m
1o
b00000000000000000000000011110011 q
b00000000000101011000010110010011 r
b00000000000000000000000000000001 s
b00001 x
b01011 y
b00000000000000000000000000010001 z
b00000000000000000000000000010100 {
#82
0o
#83
b00000000000000000000000000010100 C
b00000000000000000000000011110100 D
b00000000000000000000000000011000 E
b00000000000000000000000011110100 Q
1f
b00000000000000000000000000000000 g
0h
0i
b001 j
b00000000000000000000000011111111 k
b1100011 l
b111111111000 m
1n
1o
b11111110011001011001100011100011 r
b11111111111111111111111111111000 s
b00000000000000000000000011111111 t
b001 v
b00110 x
b10001 y
b00000000000000000000000000001100 z
b00000000000000000000000000001100 {
#84
0o
#85
b00000000000000000000000000001100 C
b00000000000000000000000000010000 E
0f
b00000000000000000000000011110100 g
1h
1i
b000 j
b00000000000000000000000000000000 k
b0010011 l
b000000000000 m
0n
1o
b00000000000001011000010100010011 r
b00000000000000000000000000000000 s
b00000000000000000000000000000000 t
b000 v
b00000 x
b01010 y
b00000000000000000000000000010000 {
#86
0o
#87
b00000000000000000000000000010000 C
b00000000000000000000000000010100 E
b00000000000000000000000011110100 P
b00000000000000000000000011110101 g
b00000000000000000000000000000001 k
b000000000001 m
1o
b00000000000000000000000011110100 q
b00000000000101011000010110010011 r
b00000000000000000000000000000001 s
b00001 x
b01011 y
b00000000000000000000000000010001 z
b00000000000000000000000000010100 {
#88
0o
#89
b00000000000000000000000000010100 C
b00000000000000000000000011110101 D
b00000000000000000000000000011000 E
b00000000000000000000000011110101 Q
1f
b00000000000000000000000000000000 g
0h
0i
b001 j
b00000000000000000000000011111111 k
b1100011 l
b111111111000 m
1n
1o
b11111110011001011001100011100011 r
b11111111111111111111111111111000 s
b00000000000000000000000011111111 t
b001 v
b00110 x
b10001 y
b00000000000000000000000000001100 z
b00000000000000000000000000001100 {
#90
0o
#91
b00000000000000000000000000001100 C
b00000000000000000000000000010000 E
0f
b00000000000000000000000011110101 g
1h
1i
b000 j
b00000000000000000000000000000000 k
b0010011 l
b000000000000 m
0n
1o
b00000000000001011000010100010011 r
b00000000000000000000000000000000 s
b00000000000000000000000000000000 t
b000 v
b00000 x
b01010 y
b00000000000000000000000000010000 {
#92
0o
#93
b00000000000000000000000000010000 C
b00000000000000000000000000010100 E
b00000000000000000000000011110101 P
b00000000000000000000000011110110 g
b00000000000000000000000000000001 k
b000000000001 m
1o
b00000000000000000000000011110101 q
b00000000000101011000010110010011 r
b00000000000000000000000000000001 s
b00001 x
b01011 y
b00000000000000000000000000010001 z
b00000000000000000000000000010100 {
#94
0o
#95
b00000000000000000000000000010100 C
b00000000000000000000000011110110 D
b00000000000000000000000000011000 E
b00000000000000000000000011110110 Q
1f
b00000000000000000000000000000000 g
0h
0i
b001 j
b00000000000000000000000011111111 k
b1100011 l
b111111111000 m
1n
1o
b11111110011001011001100011100011 r
b11111111111111111111111111111000 s
b00000000000000000000000011111111 t
b001 v
b00110 x
b10001 y
b00000000000000000000000000001100 z
b00000000000000000000000000001100 {
#96
0o
#97
b00000000000000000000000000001100 C
b00000000000000000000000000010000 E
0f
b00000000000000000000000011110110 g
1h
1i
b000 j
b00000000000000000000000000000000 k
b0010011 l
b000000000000 m
0n
1o
b00000000000001011000010100010011 r
b00000000000000000000000000000000 s
b00000000000000000000000000000000 t
b000 v
b00000 x
b01010 y
b00000000000000000000000000010000 {
#98
0o
#99
b00000000000000000000000000010000 C
b00000000000000000000000000010100 E
b00000000000000000000000011110110 P
b00000000000000000000000011110111 g
b00000000000000000000000000000001 k
b000000000001 m
1o
b00000000000000000000000011110110 q
b00000000000101011000010110010011 r
b00000000000000000000000000000001 s
b00001 x
b01011 y
b00000000000000000000000000010001 z
b00000000000000000000000000010100 {
#100
0o
#101
b00000000000000000000000000010100 C
b00000000000000000000000011110111 D
b00000000000000000000000000011000 E
b00000000000000000000000011110111 Q
1f
b00000000000000000000000000000000 g
0h
0i
b001 j
b00000000000000000000000011111111 k
b1100011 l
b111111111000 m
1n
1o
b11111110011001011001100011100011 r
b11111111111111111111111111111000 s
b00000000000000000000000011111111 t
b001 v
b00110 x
b10001 y
b00000000000000000000000000001100 z
b00000000000000000000000000001100 {
#102
0o
#103
b00000000000000000000000000001100 C
b00000000000000000000000000010000 E
0f
b00000000000000000000000011110111 g
1h
1i
b000 j
b00000000000000000000000000000000 k
b0010011 l
b000000000000 m
0n
1o
b00000000000001011000010100010011 r
b00000000000000000000000000000000 s
b00000000000000000000000000000000 t
b000 v
b00000 x
b01010 y
b00000000000000000000000000010000 {
#104
0o
#105
b00000000000000000000000000010000 C
b00000000000000000000000000010100 E
b00000000000000000000000011110111 P
b00000000000000000000000011111000 g
b00000000000000000000000000000001 k
b000000000001 m
1o
b00000000000000000000000011110111 q
b00000000000101011000010110010011 r
b00000000000000000000000000000001 s
b00001 x
b01011 y
b00000000000000000000000000010001 z
b00000000000000000000000000010100 {
#106
0o
#107
b00000000000000000000000000010100 C
b00000000000000000000000011111000 D
b00000000000000000000000000011000 E
b00000000000000000000000011111000 Q
1f
b00000000000000000000000000000000 g
0h
0i
b001 j
b00000000000000000000000011111111 k
b1100011 l
b111111111000 m
1n
1o
b11111110011001011001100011100011 r
b11111111111111111111111111111000 s
b00000000000000000000000011111111 t
b001 v
b00110 x
b10001 y
b00000000000000000000000000001100 z
b00000000000000000000000000001100 {
#108
0o
#109
b00000000000000000000000000001100 C
b00000000000000000000000000010000 E
0f
b00000000000000000000000011111000 g
1h
1i
b000 j
b00000000000000000000000000000000 k
b0010011 l
b000000000000 m
0n
1o
b00000000000001011000010100010011 r
b00000000000000000000000000000000 s
b00000000000000000000000000000000 t
b000 v
b00000 x
b01010 y
b00000000000000000000000000010000 {
#110
0o
#111
b00000000000000000000000000010000 C
b00000000000000000000000000010100 E
b00000000000000000000000011111000 P
b00000000000000000000000011111001 g
b00000000000000000000000000000001 k
b000000000001 m
1o
b00000000000000000000000011111000 q
b00000000000101011000010110010011 r
b00000000000000000000000000000001 s
b00001 x
b01011 y
b00000000000000000000000000010001 z
b00000000000000000000000000010100 {
#112
0o
#113
b00000000000000000000000000010100 C
b00000000000000000000000011111001 D
b00000000000000000000000000011000 E
b00000000000000000000000011111001 Q
1f
b00000000000000000000000000000000 g
0h
0i
b001 j
b00000000000000000000000011111111 k
b1100011 l
b111111111000 m
1n
1o
b11111110011001011001100011100011 r
b11111111111111111111111111111000 s
b00000000000000000000000011111111 t
b001 v
b00110 x
b10001 y
b00000000000000000000000000001100 z
b00000000000000000000000000001100 {
#114
0o
#115
b00000000000000000000000000001100 C
b00000000000000000000000000010000 E
0f
b00000000000000000000000011111001 g
1h
1i
b000 j
b00000000000000000000000000000000 k
b0010011 l
b000000000000 m
0n
1o
b00000000000001011000010100010011 r
b00000000000000000000000000000000 s
b00000000000000000000000000000000 t
b000 v
b00000 x
b01010 y
b00000000000000000000000000010000 {
#116
0o
#117
b00000000000000000000000000010000 C
b00000000000000000000000000010100 E
b00000000000000000000000011111001 P
b00000000000000000000000011111010 g
b00000000000000000000000000000001 k
b000000000001 m
1o
b00000000000000000000000011111001 q
b00000000000101011000010110010011 r
b00000000000000000000000000000001 s
b00001 x
b01011 y
b00000000000000000000000000010001 z
b00000000000000000000000000010100 {
#118
0o
#119
b00000000000000000000000000010100 C
b00000000000000000000000011111010 D
b00000000000000000000000000011000 E
b00000000000000000000000011111010 Q
1f
b00000000000000000000000000000000 g
0h
0i
b001 j
b00000000000000000000000011111111 k
b1100011 l
b111111111000 m
1n
1o
b11111110011001011001100011100011 r
b11111111111111111111111111111000 s
b00000000000000000000000011111111 t
b001 v
b00110 x
b10001 y
b00000000000000000000000000001100 z
b00000000000000000000000000001100 {
#120
0o
#121
b00000000000000000000000000001100 C
b00000000000000000000000000010000 E
0f
b00000000000000000000000011111010 g
1h
1i
b000 j
b00000000000000000000000000000000 k
b0010011 l
b000000000000 m
0n
1o
b00000000000001011000010100010011 r
b00000000000000000000000000000000 s
b00000000000000000000000000000000 t
b000 v
b00000 x
b01010 y
b00000000000000000000000000010000 {
#122
0o
#123
b00000000000000000000000000010000 C
b00000000000000000000000000010100 E
b00000000000000000000000011111010 P
b00000000000000000000000011111011 g
b00000000000000000000000000000001 k
b000000000001 m
1o
b00000000000000000000000011111010 q
b00000000000101011000010110010011 r
b00000000000000000000000000000001 s
b00001 x
b01011 y
b00000000000000000000000000010001 z
b00000000000000000000000000010100 {
#124
0o
#125
b00000000000000000000000000010100 C
b00000000000000000000000011111011 D
b00000000000000000000000000011000 E
b00000000000000000000000011111011 Q
1f
b00000000000000000000000000000000 g
0h
0i
b001 j
b00000000000000000000000011111111 k
b1100011 l
b111111111000 m
1n
1o
b11111110011001011001100011100011 r
b11111111111111111111111111111000 s
b00000000000000000000000011111111 t
b001 v
b00110 x
b10001 y
b00000000000000000000000000001100 z
b00000000000000000000000000001100 {
#126
0o
#127
b00000000000000000000000000001100 C
b00000000000000000000000000010000 E
0f
b00000000000000000000000011111011 g
1h
1i
b000 j
b00000000000000000000000000000000 k
b0010011 l
b000000000000 m
0n
1o
b00000000000001011000010100010011 r
b00000000000000000000000000000000 s
b00000000000000000000000000000000 t
b000 v
b00000 x
b01010 y
b00000000000000000000000000010000 {
#128
0o
#129
b00000000000000000000000000010000 C
b00000000000000000000000000010100 E
b00000000000000000000000011111011 P
b00000000000000000000000011111100 g
b00000000000000000000000000000001 k
b000000000001 m
1o
b00000000000000000000000011111011 q
b00000000000101011000010110010011 r
b00000000000000000000000000000001 s
b00001 x
b01011 y
b00000000000000000000000000010001 z
b00000000000000000000000000010100 {
#130
0o
