ALU.sv
module ALU #(
    parameter DATAWIDTH = 32
)(
    input logic [DATAWIDTH-1:0]         ALUop1,
    input logic [2:0]                   ALUctrl,
    input logic                         ALUsrc,
    input logic [DATAWIDTH-1:0]         regOp2,
    input logic [DATAWIDTH-1:0]         ImmOp,
    // input logic clk,

    output logic [DATAWIDTH-1:0]        ALUout,
    output logic Eq
);

    logic [DATAWIDTH-1:0] ALUop2;
     
always_comb begin
    ALUop2 = ALUsrc ? ImmOp : regOp2;
    case (ALUctrl)
        3'b000: ALUout = ALUop1 + ALUop2;
        3'b001: ALUout= ALUop1 - ALUop2;
        3'b010: ALUout= ALUop1 & ALUop2;
        3'b011: ALUout= ALUop1 | ALUop2;
        3'b100: ALUout= 32'b0;
        3'b101: ALUout= 32'b0;
        3'b110: ALUout= 32'b0;
        default: ALUout = 0;
    endcase
    
end
assign Eq = (ALUop1==ALUop2);
// always_ff @(posedge clk) begin
//     $display("aluop1: ",ALUop1);
//     $display("aluop2: ",ALUop2);
//     $display("eq : ",Eq);
// end


endmodule

signextendo.sv
module signextendo #(
    DW=32
) (
    input logic[2:0] ImmSrc,
    input logic [DW-1:0] instr,
    output logic [DW-1:0] ImmOp
);
    logic [11:0] immediate;
    logic msb;
    always_comb begin
        case (ImmSrc)
        3'b000:begin //imm in bit[31:20] of inst
            immediate=instr[31:20];
            msb=immediate[11];
            ImmOp={{5'd20{msb}},{immediate[11:0]}};
        end
        3'b001:begin
            immediate={instr[31],instr[7],instr[30:25],instr[11:8]};
            msb=immediate[11];
            ImmOp={{5'd20{msb}},{immediate[11:0]}};
        end
        default:begin
            ImmOp=0;
        end
        endcase
    end
    
endmodule

register_file.sv
module register_file #(
    parameter ADDRESS_WIDTH = 5,
                DATA_WIDTH = 32
)(
    input logic                             clk,
    input logic [ADDRESS_WIDTH-1:0]         AD1,
    input logic [ADDRESS_WIDTH-1:0]         AD2,
    input logic [ADDRESS_WIDTH-1:0]         AD3,
    input logic                             WE3,
    input logic [DATA_WIDTH-1:0]            WD3,

    output logic [DATA_WIDTH-1:0]           RD1,
    output logic [DATA_WIDTH-1:0]           RD2,
    output logic [DATA_WIDTH-1:0]           a0  
);
//connecting mux logic: ALUsrc ? ImmOp : regOp2;

logic [DATA_WIDTH-1:0] register_array [2**ADDRESS_WIDTH-1:0];

always_ff @(posedge clk) begin
    if (WE3) register_array[AD3] <= WD3;
   
end
always_comb begin
    RD1 = register_array[AD1];
    RD2 = register_array[AD2];
end

always_comb begin
    $display("###########################################################");
    $display("registers");
    $display("t1");
    $displayh(register_array[6]);
    $display("a0");
    $displayh(register_array[10]);
    $display("a1");
    $displayh(register_array[11]);
end

assign  a0 = register_array[10];

endmodule

control.sv
module control #(
    parameter AW=32
) (
    input logic Eq,
    input logic [AW-1:0] instr,
    output logic RegWrite,
    output logic [2:0] ALUctrl,
    output logic ALUsrc,
    output logic [2:0] ImmSrc,
    output logic PCsrc 
);
    logic [6:0] opcode;
    
    always_comb begin
        opcode=instr[6:0];
        ALUctrl=instr[14:12];
        // ALUsrc=instr[5]? 0: 1;
        case (opcode)
            7'd19: begin //store inst
                 ImmSrc=3'b000;
                 RegWrite=1'b1;
                 PCsrc=1'b0;
                 ALUsrc=1'b1;
                end
            7'd99:begin //jump instr
                ImmSrc=3'b001;
                RegWrite=1'b0;
                PCsrc=Eq?1'b0:1'b1;
                ALUsrc=1'b0;
            end
         default: begin
            ImmSrc=3'b000;
            RegWrite=1'b0;
            PCsrc=1'b0;
        end          
        endcase

    end
endmodule

ROM.sv
module ROM #(
    parameter   ADDRESS_WIDTH = 8,
                DATA_WIDTH = 8
)(
    input logic     [ADDRESS_WIDTH-1:0]         A,
    output logic    [ADDRESS_WIDTH-1:0]         RD
);

logic [DATA_WIDTH-1:0] rom_array [2**ADDRESS_WIDTH-1:0];

initial begin
    $display("Loading rom.");
    $readmemh("example_rom.mem", rom_array);
end

always_comb begin
    //output is asynchronous
    RD = rom_array[A];
end
endmodule

PC.sv
module PC #(
    DW=32

) (
    input logic     clk,
    input logic     rst,
    input logic     PCsrc,
    input logic   [DW-1:0]  ImmOp,
    output logic  [DW-1:0]  PCC
);
    
    logic [DW-1:0] inc_PC;
    logic [DW-1:0] branch_PC;
    logic [DW-1:0] next_PC;

    assign branch_PC = PCC+ImmOp;
    assign inc_PC=PCC+4;
    assign next_PC=PCsrc ? branch_PC : inc_PC;
   
    always_comb begin
        
    end

    always_ff @(posedge clk ) begin
        // $display("PC= ",PCC);
        if (rst) PCC<=32'b0;
        else PCC<=next_PC;
    end

endmodule

top.sv
module top #(
    parameter DW=32
) (
    input logic clk,
    input logic rst,
    output logic [DW-1:0] a0out,
    output logic [DW-1:0] InstructionWire,
    output logic [DW-1:0] ImmOpWire 
);

    logic PCsrsWire;
    
    logic [DW-1:0] PCWire;
    
    logic [DW-1:0] ALUoutWire;
    logic [DW-1:0] RD1Wire;
    logic [DW-1:0] RD2Wire;
    logic EQWire;
    logic RegWriteWire;
    logic ALUsrcWire;
    logic [2:0] ALUctrlWire;
    logic [2:0] ImmSrcWire;
    logic [4:0] rs1;
    logic [4:0] rs2;
    logic [4:0] rd;
    
    PC PC(
        .clk(clk),
        .rst(rst),
        .PCsrc(PCsrsWire),
        .ImmOp(ImmOpWire),
        .PCC(PCWire)
    );
    
    ROM ROM(
        .A(PCWire),
        .RD(InstructionWire)
    );
   
    assign rs1 = InstructionWire[19:15];
    assign rs2 = InstructionWire[24:20];
    assign rd = InstructionWire[11:7];
    
    control control(
        .Eq(EQWire),
        .instr(InstructionWire),
        .RegWrite(RegWriteWire),
        .ALUctrl(ALUctrlWire),
        .ALUsrc(ALUsrcWire),
        .ImmSrc(ImmSrcWire),
        .PCsrc(PCsrsWire)
    );

    register_file RegFile(
        .clk(clk),
        .AD1(rs1),
        .AD2(rs2),
        .AD3(rd),
        .WE3(RegWriteWire),
        .WD3(ALUoutWire),

        .a0(a0out),
        .RD1(RD1Wire),
        .RD2(RD2Wire)
    );
    signextendo extendo(
        .instr(InstructionWire),
        .ImmSrc(ImmSrcWire),

        .ImmOp(ImmOpWire)
    );
    ALU aluCPU(
        .ALUop1(RD1Wire),
        .ALUctrl(ALUctrlWire),
        .ALUsrc(ALUsrcWire),
        .regOp2(RD2Wire), //register
        .ImmOp(ImmOpWire), //immediate comparison done inside alu

        .ALUout(ALUoutWire),
        .Eq(EQWire)
    );
    

    
endmodule

top.vcd
$version Generated by VerilatedVcd $end
$date Wed Nov 23 14:14:18 2022 $end
$timescale 1ps $end

 $scope module TOP $end
  $var wire 32 U ImmOpWire [31:0] $end
  $var wire 32 T InstructionWire [31:0] $end
  $var wire 32 S a0out [31:0] $end
  $var wire  1 Q clk $end
  $var wire  1 R rst $end
  $scope module top $end
   $var wire  3 X ALUctrlWire [2:0] $end
   $var wire 32 I ALUoutWire [31:0] $end
   $var wire  1 K ALUsrcWire $end
   $var wire 32 ^ DW [31:0] $end
   $var wire  1 W EQWire $end
   $var wire 32 U ImmOpWire [31:0] $end
   $var wire  3 L ImmSrcWire [2:0] $end
   $var wire 32 T InstructionWire [31:0] $end
   $var wire 32 # PCWire [31:0] $end
   $var wire  1 H PCsrsWire $end
   $var wire 32 $ RD1Wire [31:0] $end
   $var wire 32 V RD2Wire [31:0] $end
   $var wire  1 J RegWriteWire $end
   $var wire 32 S a0out [31:0] $end
   $var wire  1 Q clk $end
   $var wire  5 [ rd [4:0] $end
   $var wire  5 Y rs1 [4:0] $end
   $var wire  5 Z rs2 [4:0] $end
   $var wire  1 R rst $end
   $scope module PC $end
    $var wire 32 ^ DW [31:0] $end
    $var wire 32 U ImmOp [31:0] $end
    $var wire 32 # PCC [31:0] $end
    $var wire  1 H PCsrc $end
    $var wire 32 \ branch_PC [31:0] $end
    $var wire  1 Q clk $end
    $var wire 32 % inc_PC [31:0] $end
    $var wire 32 ] next_PC [31:0] $end
    $var wire  1 R rst $end
   $upscope $end
   $scope module ROM $end
    $var wire  8 & A [7:0] $end
    $var wire 32 _ ADDRESS_WIDTH [31:0] $end
    $var wire 32 _ DATA_WIDTH [31:0] $end
    $var wire  8 ' RD [7:0] $end
   $upscope $end
   $scope module RegFile $end
    $var wire  5 Y AD1 [4:0] $end
    $var wire  5 Z AD2 [4:0] $end
    $var wire  5 [ AD3 [4:0] $end
    $var wire 32 ` ADDRESS_WIDTH [31:0] $end
    $var wire 32 ^ DATA_WIDTH [31:0] $end
    $var wire 32 $ RD1 [31:0] $end
    $var wire 32 V RD2 [31:0] $end
    $var wire 32 I WD3 [31:0] $end
    $var wire  1 J WE3 $end
    $var wire 32 S a0 [31:0] $end
    $var wire  1 Q clk $end
    $var wire 32 ( register_array[0] [31:0] $end
    $var wire 32 2 register_array[10] [31:0] $end
    $var wire 32 3 register_array[11] [31:0] $end
    $var wire 32 4 register_array[12] [31:0] $end
    $var wire 32 5 register_array[13] [31:0] $end
    $var wire 32 6 register_array[14] [31:0] $end
    $var wire 32 7 register_array[15] [31:0] $end
    $var wire 32 8 register_array[16] [31:0] $end
    $var wire 32 9 register_array[17] [31:0] $end
    $var wire 32 : register_array[18] [31:0] $end
    $var wire 32 ; register_array[19] [31:0] $end
    $var wire 32 ) register_array[1] [31:0] $end
    $var wire 32 < register_array[20] [31:0] $end
    $var wire 32 = register_array[21] [31:0] $end
    $var wire 32 > register_array[22] [31:0] $end
    $var wire 32 ? register_array[23] [31:0] $end
    $var wire 32 @ register_array[24] [31:0] $end
    $var wire 32 A register_array[25] [31:0] $end
    $var wire 32 B register_array[26] [31:0] $end
    $var wire 32 C register_array[27] [31:0] $end
    $var wire 32 D register_array[28] [31:0] $end
    $var wire 32 E register_array[29] [31:0] $end
    $var wire 32 * register_array[2] [31:0] $end
    $var wire 32 F register_array[30] [31:0] $end
    $var wire 32 G register_array[31] [31:0] $end
    $var wire 32 + register_array[3] [31:0] $end
    $var wire 32 , register_array[4] [31:0] $end
    $var wire 32 - register_array[5] [31:0] $end
    $var wire 32 . register_array[6] [31:0] $end
    $var wire 32 / register_array[7] [31:0] $end
    $var wire 32 0 register_array[8] [31:0] $end
    $var wire 32 1 register_array[9] [31:0] $end
   $upscope $end
   $scope module aluCPU $end
    $var wire  3 X ALUctrl [2:0] $end
    $var wire 32 $ ALUop1 [31:0] $end
    $var wire 32 M ALUop2 [31:0] $end
    $var wire 32 I ALUout [31:0] $end
    $var wire  1 K ALUsrc $end
    $var wire 32 ^ DATAWIDTH [31:0] $end
    $var wire  1 W Eq $end
    $var wire 32 U ImmOp [31:0] $end
    $var wire 32 V regOp2 [31:0] $end
   $upscope $end
   $scope module control $end
    $var wire  3 X ALUctrl [2:0] $end
    $var wire  1 K ALUsrc $end
    $var wire 32 ^ AW [31:0] $end
    $var wire  1 W Eq $end
    $var wire  3 L ImmSrc [2:0] $end
    $var wire  1 H PCsrc $end
    $var wire  1 J RegWrite $end
    $var wire 32 T instr [31:0] $end
    $var wire  7 N opcode [6:0] $end
   $upscope $end
   $scope module extendo $end
    $var wire 32 ^ DW [31:0] $end
    $var wire 32 U ImmOp [31:0] $end
    $var wire  3 L ImmSrc [2:0] $end
    $var wire 12 O immediate [11:0] $end
    $var wire 32 T instr [31:0] $end
    $var wire  1 P msb $end
   $upscope $end
  $upscope $end
 $upscope $end
$enddefinitions $end


#0
b00000000000000000000000000000000 #
b00000000000000000000000000000000 $
b00000000000000000000000000000100 %
b00000000 &
b00000000 '
b00000000000000000000000000000000 (
b00000000000000000000000000000000 )
b00000000000000000000000000000000 *
b00000000000000000000000000000000 +
b00000000000000000000000000000000 ,
b00000000000000000000000000000000 -
b00000000000000000000000000000000 .
b00000000000000000000000000000000 /
b00000000000000000000000000000000 0
b00000000000000000000000000000000 1
b00000000000000000000000000000000 2
b00000000000000000000000000000000 3
b00000000000000000000000000000000 4
b00000000000000000000000000000000 5
b00000000000000000000000000000000 6
b00000000000000000000000000000000 7
b00000000000000000000000000000000 8
b00000000000000000000000000000000 9
b00000000000000000000000000000000 :
b00000000000000000000000000000000 ;
b00000000000000000000000000000000 <
b00000000000000000000000000000000 =
b00000000000000000000000000000000 >
b00000000000000000000000000000000 ?
b00000000000000000000000000000000 @
b00000000000000000000000000000000 A
b00000000000000000000000000000000 B
b00000000000000000000000000000000 C
b00000000000000000000000000000000 D
b00000000000000000000000000000000 E
b00000000000000000000000000000000 F
b00000000000000000000000000000000 G
0H
b00000000000000000000000000000000 I
0J
0K
b000 L
b00000000000000000000000000000000 M
b0000000 N
b000000000000 O
0P
0Q
0R
b00000000000000000000000000000000 S
b00000000000000000000000000000000 T
b00000000000000000000000000000000 U
b00000000000000000000000000000000 V
1W
b000 X
b00000 Y
b00000 Z
b00000 [
b00000000000000000000000000000000 \
b00000000000000000000000000000100 ]
b00000000000000000000000000100000 ^
b00000000000000000000000000001000 _
b00000000000000000000000000000101 `
#1
b00001111 '
b0001111 N
1Q
b00000000000000000000000000001111 T
#2
0Q
1R
#3
1Q
#4
0Q
#5
1Q
#6
0Q
0R
#7
b00000000000000000000000000000100 #
b00000000000000000000000000001000 %
b00000100 &
b00000000 '
b0000000 N
1Q
b00000000000000000000000000000000 T
b00000000000000000000000000000100 \
b00000000000000000000000000001000 ]
#8
0Q
#9
b00000000000000000000000000001000 #
b00000000000000000000000000001100 %
b00001000 &
b00001111 '
b0001111 N
1Q
b00000000000000000000000000001111 T
b00000000000000000000000000001000 \
b00000000000000000000000000001100 ]
#10
0Q
#11
b00000000000000000000000000001100 #
b00000000000000000000000000010000 %
b00001100 &
b00000000 '
b0000000 N
1Q
b00000000000000000000000000000000 T
b00000000000000000000000000001100 \
b00000000000000000000000000010000 ]
#12
0Q
#13
b00000000000000000000000000010000 #
b00000000000000000000000000010100 %
b00010000 &
1Q
b00000000000000000000000000010000 \
b00000000000000000000000000010100 ]
#14
0Q
#15
b00000000000000000000000000010100 #
b00000000000000000000000000011000 %
b00010100 &
b11111110 '
b1111110 N
1Q
b00000000000000000000000011111110 T
b00001 [
b00000000000000000000000000010100 \
b00000000000000000000000000011000 ]
#16
0Q
#17
b00000000000000000000000000011000 #
b00000000000000000000000000011100 %
b00011000 &
1Q
b00000000000000000000000000011000 \
b00000000000000000000000000011100 ]
#18
0Q
#19
b00000000000000000000000000011100 #
b00000000000000000000000000100000 %
b00011100 &
b00000000 '
b0000000 N
1Q
b00000000000000000000000000000000 T
b00000 [
b00000000000000000000000000011100 \
b00000000000000000000000000100000 ]
#20
0Q
#21
b00000000000000000000000000100000 #
b00000000000000000000000000100100 %
b00100000 &
1Q
b00000000000000000000000000100000 \
b00000000000000000000000000100100 ]
#22
0Q
#23
b00000000000000000000000000100100 #
b00000000000000000000000000101000 %
b00100100 &
1Q
b00000000000000000000000000100100 \
b00000000000000000000000000101000 ]
#24
0Q
#25
b00000000000000000000000000101000 #
b00000000000000000000000000101100 %
b00101000 &
1Q
b00000000000000000000000000101000 \
b00000000000000000000000000101100 ]
#26
0Q
#27
b00000000000000000000000000101100 #
b00000000000000000000000000110000 %
b00101100 &
1Q
b00000000000000000000000000101100 \
b00000000000000000000000000110000 ]
#28
0Q
#29
b00000000000000000000000000110000 #
b00000000000000000000000000110100 %
b00110000 &
1Q
b00000000000000000000000000110000 \
b00000000000000000000000000110100 ]
#30
0Q
#31
b00000000000000000000000000110100 #
b00000000000000000000000000111000 %
b00110100 &
1Q
b00000000000000000000000000110100 \
b00000000000000000000000000111000 ]
#32
0Q
#33
b00000000000000000000000000111000 #
b00000000000000000000000000111100 %
b00111000 &
1Q
b00000000000000000000000000111000 \
b00000000000000000000000000111100 ]
#34
0Q
#35
b00000000000000000000000000111100 #
b00000000000000000000000001000000 %
b00111100 &
1Q
b00000000000000000000000000111100 \
b00000000000000000000000001000000 ]
#36
0Q
#37
b00000000000000000000000001000000 #
b00000000000000000000000001000100 %
b01000000 &
1Q
b00000000000000000000000001000000 \
b00000000000000000000000001000100 ]
#38
0Q
#39
b00000000000000000000000001000100 #
b00000000000000000000000001001000 %
b01000100 &
1Q
b00000000000000000000000001000100 \
b00000000000000000000000001001000 ]
#40
0Q
#41
b00000000000000000000000001001000 #
b00000000000000000000000001001100 %
b01001000 &
1Q
b00000000000000000000000001001000 \
b00000000000000000000000001001100 ]
#42
0Q
#43
b00000000000000000000000001001100 #
b00000000000000000000000001010000 %
b01001100 &
1Q
b00000000000000000000000001001100 \
b00000000000000000000000001010000 ]
#44
0Q
#45
b00000000000000000000000001010000 #
b00000000000000000000000001010100 %
b01010000 &
1Q
b00000000000000000000000001010000 \
b00000000000000000000000001010100 ]
#46
0Q
#47
b00000000000000000000000001010100 #
b00000000000000000000000001011000 %
b01010100 &
1Q
b00000000000000000000000001010100 \
b00000000000000000000000001011000 ]
#48
0Q
#49
b00000000000000000000000001011000 #
b00000000000000000000000001011100 %
b01011000 &
1Q
b00000000000000000000000001011000 \
b00000000000000000000000001011100 ]
#50
0Q
#51
b00000000000000000000000001011100 #
b00000000000000000000000001100000 %
b01011100 &
1Q
b00000000000000000000000001011100 \
b00000000000000000000000001100000 ]
#52
0Q
#53
b00000000000000000000000001100000 #
b00000000000000000000000001100100 %
b01100000 &
1Q
b00000000000000000000000001100000 \
b00000000000000000000000001100100 ]
#54
0Q
#55
b00000000000000000000000001100100 #
b00000000000000000000000001101000 %
b01100100 &
1Q
b00000000000000000000000001100100 \
b00000000000000000000000001101000 ]
#56
0Q
#57
b00000000000000000000000001101000 #
b00000000000000000000000001101100 %
b01101000 &
1Q
b00000000000000000000000001101000 \
b00000000000000000000000001101100 ]
#58
0Q
#59
b00000000000000000000000001101100 #
b00000000000000000000000001110000 %
b01101100 &
1Q
b00000000000000000000000001101100 \
b00000000000000000000000001110000 ]
#60
0Q
#61
b00000000000000000000000001110000 #
b00000000000000000000000001110100 %
b01110000 &
1Q
b00000000000000000000000001110000 \
b00000000000000000000000001110100 ]
#62
0Q
#63
b00000000000000000000000001110100 #
b00000000000000000000000001111000 %
b01110100 &
1Q
b00000000000000000000000001110100 \
b00000000000000000000000001111000 ]
#64
0Q
#65
b00000000000000000000000001111000 #
b00000000000000000000000001111100 %
b01111000 &
1Q
b00000000000000000000000001111000 \
b00000000000000000000000001111100 ]
#66
0Q
#67
b00000000000000000000000001111100 #
b00000000000000000000000010000000 %
b01111100 &
1Q
b00000000000000000000000001111100 \
b00000000000000000000000010000000 ]
#68
0Q
#69
b00000000000000000000000010000000 #
b00000000000000000000000010000100 %
b10000000 &
1Q
b00000000000000000000000010000000 \
b00000000000000000000000010000100 ]
#70
0Q
#71
b00000000000000000000000010000100 #
b00000000000000000000000010001000 %
b10000100 &
1Q
b00000000000000000000000010000100 \
b00000000000000000000000010001000 ]
#72
0Q
#73
b00000000000000000000000010001000 #
b00000000000000000000000010001100 %
b10001000 &
1Q
b00000000000000000000000010001000 \
b00000000000000000000000010001100 ]
#146
0Q
#147
b00000000000000000000000010001100 #
b00000000000000000000000010010000 %
b10001100 &
1Q
b00000000000000000000000010001100 \
b00000000000000000000000010010000 ]
#148
0Q
#149
b00000000000000000000000010010000 #
b00000000000000000000000010010100 %
b10010000 &
1Q
b00000000000000000000000010010000 \
b00000000000000000000000010010100 ]
#150
0Q
#151
b00000000000000000000000010010100 #
b00000000000000000000000010011000 %
b10010100 &
1Q
b00000000000000000000000010010100 \
b00000000000000000000000010011000 ]
#152
0Q
#153
b00000000000000000000000010011000 #
b00000000000000000000000010011100 %
b10011000 &
1Q
b00000000000000000000000010011000 \
b00000000000000000000000010011100 ]
#154
0Q
#155
b00000000000000000000000010011100 #
b00000000000000000000000010100000 %
b10011100 &
1Q
b00000000000000000000000010011100 \
b00000000000000000000000010100000 ]
#156
0Q
#157
b00000000000000000000000010100000 #
b00000000000000000000000010100100 %
b10100000 &
1Q
b00000000000000000000000010100000 \
b00000000000000000000000010100100 ]
#158
0Q
#159
b00000000000000000000000010100100 #
b00000000000000000000000010101000 %
b10100100 &
1Q
b00000000000000000000000010100100 \
b00000000000000000000000010101000 ]
#160
0Q
#161
b00000000000000000000000010101000 #
b00000000000000000000000010101100 %
b10101000 &
1Q
b00000000000000000000000010101000 \
b00000000000000000000000010101100 ]
#162
0Q
#163
b00000000000000000000000010101100 #
b00000000000000000000000010110000 %
b10101100 &
1Q
b00000000000000000000000010101100 \
b00000000000000000000000010110000 ]
#164
0Q
#165
b00000000000000000000000010110000 #
b00000000000000000000000010110100 %
b10110000 &
1Q
b00000000000000000000000010110000 \
b00000000000000000000000010110100 ]
#166
0Q
#167
b00000000000000000000000010110100 #
b00000000000000000000000010111000 %
b10110100 &
1Q
b00000000000000000000000010110100 \
b00000000000000000000000010111000 ]
#168
0Q
#169
b00000000000000000000000010111000 #
b00000000000000000000000010111100 %
b10111000 &
1Q
b00000000000000000000000010111000 \
b00000000000000000000000010111100 ]
#170
0Q
#171
b00000000000000000000000010111100 #
b00000000000000000000000011000000 %
b10111100 &
1Q
b00000000000000000000000010111100 \
b00000000000000000000000011000000 ]
#172
0Q
#173
b00000000000000000000000011000000 #
b00000000000000000000000011000100 %
b11000000 &
1Q
b00000000000000000000000011000000 \
b00000000000000000000000011000100 ]
#174
0Q
#175
b00000000000000000000000011000100 #
b00000000000000000000000011001000 %
b11000100 &
1Q
b00000000000000000000000011000100 \
b00000000000000000000000011001000 ]
#176
0Q
#736
b00000000000000000000000011001000 #
b00000000000000000000000011001100 %
b11001000 &
1Q
b00000000000000000000000011001000 \
b00000000000000000000000011001100 ]
#737
0Q
#738
b00000000000000000000000011001100 #
b00000000000000000000000011010000 %
b11001100 &
1Q
b00000000000000000000000011001100 \
b00000000000000000000000011010000 ]
#739
0Q
#740
b00000000000000000000000011010000 #
b00000000000000000000000011010100 %
b11010000 &
1Q
b00000000000000000000000011010000 \
b00000000000000000000000011010100 ]
#741
0Q
#742
b00000000000000000000000011010100 #
b00000000000000000000000011011000 %
b11010100 &
1Q
b00000000000000000000000011010100 \
b00000000000000000000000011011000 ]
#743
0Q
#752
b00000000000000000000000011011000 #
b00000000000000000000000011011100 %
b11011000 &
1Q
b00000000000000000000000011011000 \
b00000000000000000000000011011100 ]
#753
0Q
#754
b00000000000000000000000011011100 #
b00000000000000000000000011100000 %
b11011100 &
1Q
b00000000000000000000000011011100 \
b00000000000000000000000011100000 ]
#755
0Q
#756
b00000000000000000000000011100000 #
b00000000000000000000000011100100 %
b11100000 &
1Q
b00000000000000000000000011100000 \
b00000000000000000000000011100100 ]
#757
0Q
#766
b00000000000000000000000011100100 #
b00000000000000000000000011101000 %
b11100100 &
1Q
b00000000000000000000000011100100 \
b00000000000000000000000011101000 ]
#767
0Q
#768
b00000000000000000000000011101000 #
b00000000000000000000000011101100 %
b11101000 &
1Q
b00000000000000000000000011101000 \
b00000000000000000000000011101100 ]
#769
0Q
#770
b00000000000000000000000011101100 #
b00000000000000000000000011110000 %
b11101100 &
1Q
b00000000000000000000000011101100 \
b00000000000000000000000011110000 ]
#771
0Q
#772
b00000000000000000000000011110000 #
b00000000000000000000000011110100 %
b11110000 &
1Q
b00000000000000000000000011110000 \
b00000000000000000000000011110100 ]
#773
0Q
#774
b00000000000000000000000011110100 #
b00000000000000000000000011111000 %
b11110100 &
1Q
b00000000000000000000000011110100 \
b00000000000000000000000011111000 ]
#775
0Q
#776
b00000000000000000000000011111000 #
b00000000000000000000000011111100 %
b11111000 &
1Q
b00000000000000000000000011111000 \
b00000000000000000000000011111100 ]
#777
0Q
#778
b00000000000000000000000011111100 #
b00000000000000000000000100000000 %
b11111100 &
1Q
b00000000000000000000000011111100 \
b00000000000000000000000100000000 ]
#779
0Q
#780
b00000000000000000000000100000000 #
b00000000000000000000000100000100 %
b00000000 &
b00001111 '
b0001111 N
1Q
b00000000000000000000000000001111 T
b00000000000000000000000100000000 \
b00000000000000000000000100000100 ]
#781
0Q
#782
b00000000000000000000000100000100 #
b00000000000000000000000100001000 %
b00000100 &
b00000000 '
b0000000 N
1Q
b00000000000000000000000000000000 T
b00000000000000000000000100000100 \
b00000000000000000000000100001000 ]
#783
0Q
#784
b00000000000000000000000100001000 #
b00000000000000000000000100001100 %
b00001000 &
b00001111 '
b0001111 N
1Q
b00000000000000000000000000001111 T
b00000000000000000000000100001000 \
b00000000000000000000000100001100 ]
#785
0Q
#786
b00000000000000000000000100001100 #
b00000000000000000000000100010000 %
b00001100 &
b00000000 '
b0000000 N
1Q
b00000000000000000000000000000000 T
b00000000000000000000000100001100 \
b00000000000000000000000100010000 ]
#787
0Q
#788
b00000000000000000000000100010000 #
b00000000000000000000000100010100 %
b00010000 &
1Q
b00000000000000000000000100010000 \
b00000000000000000000000100010100 ]
#789
0Q
#790
b00000000000000000000000100010100 #
b00000000000000000000000100011000 %
b00010100 &
b11111110 '
b1111110 N
1Q
b00000000000000000000000011111110 T
b00001 [
b00000000000000000000000100010100 \
b00000000000000000000000100011000 ]
#791
0Q
#792
b00000000000000000000000100011000 #
b00000000000000000000000100011100 %
b00011000 &
1Q
b00000000000000000000000100011000 \
b00000000000000000000000100011100 ]
#793
0Q
#794
b00000000000000000000000100011100 #
b00000000000000000000000100100000 %
b00011100 &
b00000000 '
b0000000 N
1Q
b00000000000000000000000000000000 T
b00000 [
b00000000000000000000000100011100 \
b00000000000000000000000100100000 ]
#795
0Q
#796
b00000000000000000000000100100000 #
b00000000000000000000000100100100 %
b00100000 &
1Q
b00000000000000000000000100100000 \
b00000000000000000000000100100100 ]
#797
0Q
#798
b00000000000000000000000100100100 #
b00000000000000000000000100101000 %
b00100100 &
1Q
b00000000000000000000000100100100 \
b00000000000000000000000100101000 ]
#799
0Q
#800
b00000000000000000000000100101000 #
b00000000000000000000000100101100 %
b00101000 &
1Q
b00000000000000000000000100101000 \
b00000000000000000000000100101100 ]
#801
0Q
#802
b00000000000000000000000100101100 #
b00000000000000000000000100110000 %
b00101100 &
1Q
b00000000000000000000000100101100 \
b00000000000000000000000100110000 ]
#803
0Q
#804
b00000000000000000000000100110000 #
b00000000000000000000000100110100 %
b00110000 &
1Q
b00000000000000000000000100110000 \
b00000000000000000000000100110100 ]
#805
0Q
#806
b00000000000000000000000100110100 #
b00000000000000000000000100111000 %
b00110100 &
1Q
b00000000000000000000000100110100 \
b00000000000000000000000100111000 ]
#807
0Q
#808
b00000000000000000000000100111000 #
b00000000000000000000000100111100 %
b00111000 &
1Q
b00000000000000000000000100111000 \
b00000000000000000000000100111100 ]
#809
0Q
#810
b00000000000000000000000100111100 #
b00000000000000000000000101000000 %
b00111100 &
1Q
b00000000000000000000000100111100 \
b00000000000000000000000101000000 ]
#811
0Q
#812
b00000000000000000000000101000000 #
b00000000000000000000000101000100 %
b01000000 &
1Q
b00000000000000000000000101000000 \
b00000000000000000000000101000100 ]
#813
0Q
#814
b00000000000000000000000101000100 #
b00000000000000000000000101001000 %
b01000100 &
1Q
b00000000000000000000000101000100 \
b00000000000000000000000101001000 ]
#815
0Q
#816
b00000000000000000000000101001000 #
b00000000000000000000000101001100 %
b01001000 &
1Q
b00000000000000000000000101001000 \
b00000000000000000000000101001100 ]
#817
0Q
#818
b00000000000000000000000101001100 #
b00000000000000000000000101010000 %
b01001100 &
1Q
b00000000000000000000000101001100 \
b00000000000000000000000101010000 ]
#819
0Q
#820
b00000000000000000000000101010000 #
b00000000000000000000000101010100 %
b01010000 &
1Q
b00000000000000000000000101010000 \
b00000000000000000000000101010100 ]
#821
0Q
#822
b00000000000000000000000101010100 #
b00000000000000000000000101011000 %
b01010100 &
1Q
b00000000000000000000000101010100 \
b00000000000000000000000101011000 ]
#823
0Q
#824
b00000000000000000000000101011000 #
b00000000000000000000000101011100 %
b01011000 &
1Q
b00000000000000000000000101011000 \
b00000000000000000000000101011100 ]
#825
0Q
#826
b00000000000000000000000101011100 #
b00000000000000000000000101100000 %
b01011100 &
1Q
b00000000000000000000000101011100 \
b00000000000000000000000101100000 ]
#827
0Q
#828
b00000000000000000000000101100000 #
b00000000000000000000000101100100 %
b01100000 &
1Q
b00000000000000000000000101100000 \
b00000000000000000000000101100100 ]
#829
0Q
#830
b00000000000000000000000101100100 #
b00000000000000000000000101101000 %
b01100100 &
1Q
b00000000000000000000000101100100 \
b00000000000000000000000101101000 ]
#831
0Q
#832
b00000000000000000000000101101000 #
b00000000000000000000000101101100 %
b01101000 &
1Q
b00000000000000000000000101101000 \
b00000000000000000000000101101100 ]
#833
0Q
#834
b00000000000000000000000101101100 #
b00000000000000000000000101110000 %
b01101100 &
1Q
b00000000000000000000000101101100 \
b00000000000000000000000101110000 ]
#835
0Q
#836
b00000000000000000000000101110000 #
b00000000000000000000000101110100 %
b01110000 &
1Q
b00000000000000000000000101110000 \
b00000000000000000000000101110100 ]
#837
0Q
#838
b00000000000000000000000101110100 #
b00000000000000000000000101111000 %
b01110100 &
1Q
b00000000000000000000000101110100 \
b00000000000000000000000101111000 ]
#839
0Q
#840
b00000000000000000000000101111000 #
b00000000000000000000000101111100 %
b01111000 &
1Q
b00000000000000000000000101111000 \
b00000000000000000000000101111100 ]
#841
0Q
#842
b00000000000000000000000101111100 #
b00000000000000000000000110000000 %
b01111100 &
1Q
b00000000000000000000000101111100 \
b00000000000000000000000110000000 ]
#843
0Q
#844
b00000000000000000000000110000000 #
b00000000000000000000000110000100 %
b10000000 &
1Q
b00000000000000000000000110000000 \
b00000000000000000000000110000100 ]
#845
0Q
#846
b00000000000000000000000110000100 #
b00000000000000000000000110001000 %
b10000100 &
1Q
b00000000000000000000000110000100 \
b00000000000000000000000110001000 ]
#847
0Q
#848
b00000000000000000000000110001000 #
b00000000000000000000000110001100 %
b10001000 &
1Q
b00000000000000000000000110001000 \
b00000000000000000000000110001100 ]
#849
0Q
